[{"__type__":"cc.Prefab","_name":"effect_fire_up","data":{"__id__":1}},{"__type__":"cc.Node","_name":"effect_fire_up","_components":[{"__type__":"cc.Sprite","node":{"__id__":1},"_materials":[{"__uuid__":"ecpdLyjvZBwrvm+cedCcQy"}],"_spriteFrame":{"__uuid__":"922B+my01CdZlerljK3uTK"},"_sizeMode":0,"_isTrimmedMode":false},{"__type__":"cc.Animation","node":{"__id__":1},"_defaultClip":{"__uuid__":"5b9MGOVFlC4JNza3MI9zUC"},"_clips":[{"__uuid__":"5b9MGOVFlC4JNza3MI9zUC"}]},{"__type__":"cc.Widget","node":{"__id__":1},"_alignFlags":41,"_left":-39,"_right":-69,"_top":-176,"_originalWidth":311}],"_prefab":{"__type__":"cc.PrefabInfo","root":{"__id__":1},"asset":{"__uuid__":"a9CxlfFwVEvb/dD1/zmRLA"},"fileId":"efrnuiDNdPZ7V6uIr9az9m"},"_contentSize":{"__type__":"cc.Size","width":528,"height":181},"_anchorPoint":{"__type__":"cc.Vec2","x":0.5},"_trs":{"__type__":"TypedArray","ctor":"Float64Array","array":[15,379,0,0,0,0,1,1,1,1]}}]