[{"__type__":"cc.SpriteFrame","content":{"name":"11","texture":"bes7UAV/JDAIiRkZXzFUtu","rect":[0,0,424,566],"offset":[0,0],"originalSize":[424,566],"capInsets":[0,0,0,0]}},[{"__type__":"cc.Prefab","_name":"LMSlots_BigSymbol","data":{"__id__":1}},{"__type__":"cc.Node","_name":"LMSlots_BigSymbol","_children":[{"__type__":"cc.Node","_name":"s0","_parent":{"__id__":1},"_active":false,"_prefab":{"__type__":"cc.PrefabInfo","root":{"__id__":1},"asset":{"__uuid__":"1eZVHjbCFGp5bhhP0xK23w"},"fileId":"7d7JJX7gtHA5flYHOhQjIS"},"_contentSize":{"__type__":"cc.Size","width":430,"height":520},"_trs":{"__type__":"TypedArray","ctor":"Float64Array","array":[0,0,0,0,0,0,1,0.5,0.5,0.5]}},{"__id__":2},{"__id__":3},{"__id__":4},{"__id__":5},{"__id__":6}],"_prefab":{"__type__":"cc.PrefabInfo","root":{"__id__":1},"asset":{"__uuid__":"1eZVHjbCFGp5bhhP0xK23w"},"fileId":"69Y4bR9hVM2apMbGLkGI1c"},"_trs":{"__type__":"TypedArray","ctor":"Float64Array","array":[0,-360.597,0,0,0,0,1,1,1,1]}},{"__type__":"cc.Node","_name":"s1","_parent":{"__id__":1},"_active":false,"_components":[{"__type__":"cc.Sprite","_name":"s1<Sprite>","node":{"__id__":2},"_materials":[{"__uuid__":"ecpdLyjvZBwrvm+cedCcQy"}],"_spriteFrame":{"__uuid__":"46r8U5RQlLIYnMixTkvIa7"},"_sizeMode":2,"_isTrimmedMode":false}],"_prefab":{"__type__":"cc.PrefabInfo","root":{"__id__":1},"asset":{"__uuid__":"1eZVHjbCFGp5bhhP0xK23w"},"fileId":"14+oFcU+NAlLLZYw+t+doi"},"_contentSize":{"__type__":"cc.Size","width":424,"height":565},"_trs":{"__type__":"TypedArray","ctor":"Float64Array","array":[0,9,0,0,0,0,1,0.5,0.5,1]}},{"__type__":"cc.Node","_name":"w1","_parent":{"__id__":1},"_active":false,"_components":[{"__type__":"sp.Skeleton","_name":"w1<Skeleton>","node":{"__id__":3},"_materials":[{"__uuid__":"7a/QZLET9IDreTiBfRn2PD"}],"defaultSkin":"default","defaultAnimation":"idleframe","_preCacheMode":0,"loop":false,"premultipliedAlpha":false,"_animationName":"idleframe","_playTimes":1,"_N$skeletonData":{"__uuid__":"26FuoeFnJG+6NJ6UeR6fCB"}}],"_prefab":{"__type__":"cc.PrefabInfo","root":{"__id__":1},"asset":{"__uuid__":"1eZVHjbCFGp5bhhP0xK23w"},"fileId":"25ao3UgjVGL4O/jtc6+HXW"},"_contentSize":{"__type__":"cc.Size","width":426.72,"height":552.86},"_trs":{"__type__":"TypedArray","ctor":"Float64Array","array":[0,8.267,0,0,0,0,1,0.5,0.5,1]}},{"__type__":"cc.Node","_name":"s101","_parent":{"__id__":1},"_active":false,"_components":[{"__type__":"cc.Sprite","_name":"s101<Sprite>","node":{"__id__":4},"_materials":[{"__uuid__":"ecpdLyjvZBwrvm+cedCcQy"}],"_spriteFrame":{"__uuid__":"02v+2D1VVH+LnMuEof+qyf"},"_sizeMode":2,"_isTrimmedMode":false}],"_prefab":{"__type__":"cc.PrefabInfo","root":{"__id__":1},"asset":{"__uuid__":"1eZVHjbCFGp5bhhP0xK23w"},"fileId":"c5jyS196NDEagmo+1c7Vrl"},"_contentSize":{"__type__":"cc.Size","width":424,"height":566},"_trs":{"__type__":"TypedArray","ctor":"Float64Array","array":[0,9,0,0,0,0,1,0.5,0.5,1]}},{"__type__":"cc.Node","_name":"w101","_parent":{"__id__":1},"_active":false,"_components":[{"__type__":"sp.Skeleton","_name":"w101<Skeleton>","node":{"__id__":5},"_materials":[{"__uuid__":"7a/QZLET9IDreTiBfRn2PD"}],"defaultSkin":"default","defaultAnimation":"idleframe","_preCacheMode":0,"loop":false,"premultipliedAlpha":false,"_animationName":"idleframe","_playTimes":1,"_N$skeletonData":{"__uuid__":"b67hnVFxpICKLTCjDPUoga"}}],"_prefab":{"__type__":"cc.PrefabInfo","root":{"__id__":1},"asset":{"__uuid__":"1eZVHjbCFGp5bhhP0xK23w"},"fileId":"d7NtAEzG5ATL9sNmEYKNCA"},"_contentSize":{"__type__":"cc.Size","width":426.72,"height":552.86},"_trs":{"__type__":"TypedArray","ctor":"Float64Array","array":[0,8.267,0,0,0,0,1,0.5,0.5,1]}},{"__type__":"cc.Node","_name":"label","_parent":{"__id__":1},"_active":false,"_components":[{"__type__":"cc.Label","node":{"__id__":6},"_materials":[{"__uuid__":"ecpdLyjvZBwrvm+cedCcQy"}],"_useOriginalSize":false,"_string":"123M","_N$string":"123M","_fontSize":32,"_lineHeight":32,"_N$file":{"__uuid__":"ffDNdjnolKLrFUqYlErbpJ"},"_isSystemFontUsed":false,"_N$horizontalAlign":1,"_N$verticalAlign":1}],"_prefab":{"__type__":"cc.PrefabInfo","root":{"__id__":1},"asset":{"__uuid__":"1eZVHjbCFGp5bhhP0xK23w"},"fileId":"289vSh989OibnIMgjHuD1M"},"_contentSize":{"__type__":"cc.Size","width":104,"height":32},"_trs":{"__type__":"TypedArray","ctor":"Float64Array","array":[0,-47.88,0,0,0,0,1,1,1,1]}}],{"__type__":"cc.SpriteFrame","content":{"name":"12","texture":"e5JzusrsZOKYEe70x7378n","rect":[0,0,424,565],"offset":[0,0],"originalSize":[424,565],"capInsets":[0,0,0,0]}}]