{"__type__":"sp.SkeletonData","_name":"jiedian2","_skeletonJson":{"skeleton":{"hash":"p6wNY6+BWkOQ4DQo2SBbxfzcUj8","spine":"3.6.53","width":0,"height":0,"images":"./img/"},"bones":[{"name":"root"},{"name":"baolizi","parent":"root","scaleX":2,"scaleY":2},{"name":"baolizi2","parent":"root","scaleX":2,"scaleY":2},{"name":"jiedian","parent":"root"},{"name":"jiedian2","parent":"root"},{"name":"sao","parent":"root","y":14.54,"scaleX":3.828,"scaleY":3.828}],"slots":[{"name":"theme211_map_3","bone":"jiedian"},{"name":"theme211_map_4","bone":"jiedian2","blend":"additive"},{"name":"sao","bone":"sao","blend":"additive"},{"name":"baolizi","bone":"baolizi"},{"name":"baolizi2","bone":"baolizi2","blend":"additive"}],"skins":{"default":{"baolizi":{"baolizi/baolizi_00":{"width":140,"height":132},"baolizi/baolizi_01":{"width":151,"height":142},"baolizi/baolizi_02":{"width":162,"height":151},"baolizi/baolizi_03":{"width":171,"height":161},"baolizi/baolizi_04":{"width":179,"height":169},"baolizi/baolizi_05":{"width":186,"height":175},"baolizi/baolizi_06":{"width":192,"height":181},"baolizi/baolizi_07":{"width":198,"height":187},"baolizi/baolizi_08":{"width":203,"height":190},"baolizi/baolizi_09":{"width":208,"height":195},"baolizi/baolizi_10":{"width":210,"height":198},"baolizi/baolizi_11":{"width":214,"height":201},"baolizi/baolizi_12":{"width":214,"height":203},"baolizi/baolizi_13":{"width":217,"height":201},"baolizi/baolizi_14":{"width":216,"height":202},"baolizi/baolizi_15":{"width":202,"height":173},"baolizi/baolizi_16":{"width":196,"height":168}},"baolizi2":{"baolizi/baolizi_00":{"width":140,"height":132},"baolizi/baolizi_01":{"width":151,"height":142},"baolizi/baolizi_02":{"width":162,"height":151},"baolizi/baolizi_03":{"width":171,"height":161},"baolizi/baolizi_04":{"width":179,"height":169},"baolizi/baolizi_05":{"width":186,"height":175},"baolizi/baolizi_06":{"width":192,"height":181},"baolizi/baolizi_07":{"width":198,"height":187},"baolizi/baolizi_08":{"width":203,"height":190},"baolizi/baolizi_09":{"width":208,"height":195},"baolizi/baolizi_10":{"width":210,"height":198},"baolizi/baolizi_11":{"width":214,"height":201},"baolizi/baolizi_12":{"width":214,"height":203},"baolizi/baolizi_13":{"width":217,"height":201},"baolizi/baolizi_14":{"width":216,"height":202},"baolizi/baolizi_15":{"width":202,"height":173},"baolizi/baolizi_16":{"width":196,"height":168}},"sao":{"sao2/sao2_00":{"width":120,"height":129},"sao2/sao2_02":{"width":120,"height":129},"sao2/sao2_04":{"width":120,"height":129},"sao2/sao2_06":{"width":120,"height":129},"sao2/sao2_07":{"width":120,"height":129},"sao2/sao2_09":{"width":120,"height":129},"sao2/sao2_11":{"width":120,"height":129},"sao2/sao2_13":{"width":120,"height":129},"sao2/sao2_14":{"width":120,"height":129},"sao2/sao2_16":{"width":120,"height":129},"sao2/sao2_18":{"width":120,"height":129},"sao2/sao2_20":{"width":120,"height":129},"sao2/sao2_21":{"width":120,"height":129},"sao2/sao2_23":{"width":120,"height":129},"sao2/sao2_25":{"width":120,"height":129},"sao2/sao2_27":{"width":120,"height":129},"sao2/sao2_28":{"width":120,"height":129},"sao2/sao2_30":{"width":120,"height":129}},"theme211_map_3":{"theme211_map_4":{"width":283,"height":341}},"theme211_map_4":{"theme211_map_4":{"width":283,"height":341}}}},"animations":{"animation1":{"slots":{"sao":{"color":[{"time":1,"color":"ffffffff"},{"time":1.1667,"color":"ffffff00"}],"attachment":[{"time":0,"name":"sao2/sao2_00"},{"time":0.0667,"name":"sao2/sao2_02"},{"time":0.1333,"name":"sao2/sao2_04"},{"time":0.2,"name":"sao2/sao2_06"},{"time":0.2333,"name":"sao2/sao2_07"},{"time":0.3,"name":"sao2/sao2_09"},{"time":0.3667,"name":"sao2/sao2_11"},{"time":0.4333,"name":"sao2/sao2_13"},{"time":0.4667,"name":"sao2/sao2_14"},{"time":0.5333,"name":"sao2/sao2_16"},{"time":0.6,"name":"sao2/sao2_18"},{"time":0.6667,"name":"sao2/sao2_20"},{"time":0.7,"name":"sao2/sao2_21"},{"time":0.7667,"name":"sao2/sao2_23"},{"time":0.8333,"name":"sao2/sao2_25"},{"time":0.9,"name":"sao2/sao2_27"},{"time":0.9333,"name":"sao2/sao2_28"},{"time":1,"name":"sao2/sao2_30"},{"time":1.1667,"name":null},{"time":2.3333,"name":null}]},"theme211_map_3":{"attachment":[{"time":0,"name":"theme211_map_4"}]}}},"animation2":{"slots":{"baolizi":{"attachment":[{"time":0,"name":"baolizi/baolizi_00"},{"time":0.0333,"name":"baolizi/baolizi_01"},{"time":0.0667,"name":"baolizi/baolizi_02"},{"time":0.1,"name":"baolizi/baolizi_03"},{"time":0.1333,"name":"baolizi/baolizi_04"},{"time":0.1667,"name":"baolizi/baolizi_05"},{"time":0.2,"name":"baolizi/baolizi_06"},{"time":0.2333,"name":"baolizi/baolizi_07"},{"time":0.2667,"name":"baolizi/baolizi_08"},{"time":0.3,"name":"baolizi/baolizi_09"},{"time":0.3333,"name":"baolizi/baolizi_10"},{"time":0.3667,"name":"baolizi/baolizi_11"},{"time":0.4,"name":"baolizi/baolizi_12"},{"time":0.4333,"name":"baolizi/baolizi_13"},{"time":0.4667,"name":"baolizi/baolizi_14"},{"time":0.5,"name":"baolizi/baolizi_15"},{"time":0.5333,"name":"baolizi/baolizi_16"},{"time":0.5667,"name":null}]},"baolizi2":{"attachment":[{"time":0,"name":"baolizi/baolizi_00"},{"time":0.0333,"name":"baolizi/baolizi_01"},{"time":0.0667,"name":"baolizi/baolizi_02"},{"time":0.1,"name":"baolizi/baolizi_03"},{"time":0.1333,"name":"baolizi/baolizi_04"},{"time":0.1667,"name":"baolizi/baolizi_05"},{"time":0.2,"name":"baolizi/baolizi_06"},{"time":0.2333,"name":"baolizi/baolizi_07"},{"time":0.2667,"name":"baolizi/baolizi_08"},{"time":0.3,"name":"baolizi/baolizi_09"},{"time":0.3333,"name":"baolizi/baolizi_10"},{"time":0.3667,"name":"baolizi/baolizi_11"},{"time":0.4,"name":"baolizi/baolizi_12"},{"time":0.4333,"name":"baolizi/baolizi_13"},{"time":0.4667,"name":"baolizi/baolizi_14"},{"time":0.5,"name":"baolizi/baolizi_15"},{"time":0.5333,"name":"baolizi/baolizi_16"},{"time":0.5667,"name":null}]},"theme211_map_3":{"attachment":[{"time":0,"name":"theme211_map_4"}]},"theme211_map_4":{"color":[{"time":0,"color":"ff820000","curve":[0.25,0,0.75,1]},{"time":0.1667,"color":"fff9cdff","curve":[0.25,0,0.75,1]},{"time":0.5,"color":"ff820000"}],"attachment":[{"time":0,"name":"theme211_map_4"}]}},"bones":{"baolizi":{"translate":[{"time":0,"x":13.84,"y":-3.95}]},"baolizi2":{"translate":[{"time":0,"x":13.84,"y":-3.95}]},"jiedian":{"scale":[{"time":0,"x":1,"y":1,"curve":[0.25,0,0.75,1]},{"time":0.1667,"x":1.227,"y":1.227,"curve":[0.25,0,0.75,1]},{"time":0.5,"x":1,"y":1}]},"jiedian2":{"scale":[{"time":0,"x":1,"y":1,"curve":[0.25,0,0.75,1]},{"time":0.1667,"x":1.227,"y":1.227,"curve":[0.25,0,0.75,1]},{"time":0.5,"x":1,"y":1}]}}},"animation3":{"slots":{"theme211_map_3":{"attachment":[{"time":0,"name":"theme211_map_4"}]}}}}},"_atlasText":"\njiedian2.png\nsize: 2048,512\nformat: RGBA8888\nfilter: Linear,Linear\nrepeat: none\nbaolizi/baolizi_00\n  rotate: false\n  xy: 549, 175\n  size: 140, 132\n  orig: 140, 132\n  offset: 0, 0\n  index: -1\nbaolizi/baolizi_01\n  rotate: true\n  xy: 526, 19\n  size: 151, 142\n  orig: 151, 142\n  offset: 0, 0\n  index: -1\nbaolizi/baolizi_02\n  rotate: true\n  xy: 175, 5\n  size: 162, 151\n  orig: 162, 151\n  offset: 0, 0\n  index: -1\nbaolizi/baolizi_03\n  rotate: false\n  xy: 2, 6\n  size: 171, 161\n  orig: 171, 161\n  offset: 0, 0\n  index: -1\nbaolizi/baolizi_04\n  rotate: false\n  xy: 670, 4\n  size: 179, 169\n  orig: 179, 169\n  offset: 0, 0\n  index: -1\nbaolizi/baolizi_05\n  rotate: false\n  xy: 1055, 4\n  size: 186, 175\n  orig: 186, 175\n  offset: 0, 0\n  index: -1\nbaolizi/baolizi_06\n  rotate: false\n  xy: 1487, 6\n  size: 192, 181\n  orig: 192, 181\n  offset: 0, 0\n  index: -1\nbaolizi/baolizi_07\n  rotate: false\n  xy: 1553, 323\n  size: 198, 187\n  orig: 198, 187\n  offset: 0, 0\n  index: -1\nbaolizi/baolizi_08\n  rotate: false\n  xy: 1348, 320\n  size: 203, 190\n  orig: 203, 190\n  offset: 0, 0\n  index: -1\nbaolizi/baolizi_09\n  rotate: false\n  xy: 1138, 315\n  size: 208, 195\n  orig: 208, 195\n  offset: 0, 0\n  index: -1\nbaolizi/baolizi_10\n  rotate: false\n  xy: 926, 312\n  size: 210, 198\n  orig: 210, 198\n  offset: 0, 0\n  index: -1\nbaolizi/baolizi_11\n  rotate: false\n  xy: 710, 309\n  size: 214, 201\n  orig: 214, 201\n  offset: 0, 0\n  index: -1\nbaolizi/baolizi_12\n  rotate: false\n  xy: 1803, 45\n  size: 214, 203\n  orig: 214, 203\n  offset: 0, 0\n  index: -1\nbaolizi/baolizi_13\n  rotate: false\n  xy: 491, 309\n  size: 217, 201\n  orig: 217, 201\n  offset: 0, 0\n  index: -1\nbaolizi/baolizi_14\n  rotate: true\n  xy: 287, 294\n  size: 216, 202\n  orig: 216, 202\n  offset: 0, 0\n  index: -1\nbaolizi/baolizi_15\n  rotate: false\n  xy: 851, 3\n  size: 202, 173\n  orig: 202, 173\n  offset: 0, 0\n  index: -1\nbaolizi/baolizi_16\n  rotate: false\n  xy: 328, 2\n  size: 196, 168\n  orig: 196, 168\n  offset: 0, 0\n  index: -1\nsao2/sao2_00\n  rotate: true\n  xy: 287, 172\n  size: 120, 129\n  orig: 120, 129\n  offset: 0, 0\n  index: -1\nsao2/sao2_02\n  rotate: true\n  xy: 418, 172\n  size: 120, 129\n  orig: 120, 129\n  offset: 0, 0\n  index: -1\nsao2/sao2_04\n  rotate: false\n  xy: 691, 178\n  size: 120, 129\n  orig: 120, 129\n  offset: 0, 0\n  index: -1\nsao2/sao2_06\n  rotate: false\n  xy: 813, 178\n  size: 120, 129\n  orig: 120, 129\n  offset: 0, 0\n  index: -1\nsao2/sao2_07\n  rotate: false\n  xy: 935, 181\n  size: 120, 129\n  orig: 120, 129\n  offset: 0, 0\n  index: -1\nsao2/sao2_09\n  rotate: false\n  xy: 1057, 181\n  size: 120, 129\n  orig: 120, 129\n  offset: 0, 0\n  index: -1\nsao2/sao2_11\n  rotate: false\n  xy: 1179, 184\n  size: 120, 129\n  orig: 120, 129\n  offset: 0, 0\n  index: -1\nsao2/sao2_13\n  rotate: false\n  xy: 1243, 53\n  size: 120, 129\n  orig: 120, 129\n  offset: 0, 0\n  index: -1\nsao2/sao2_14\n  rotate: false\n  xy: 1301, 184\n  size: 120, 129\n  orig: 120, 129\n  offset: 0, 0\n  index: -1\nsao2/sao2_16\n  rotate: false\n  xy: 1365, 53\n  size: 120, 129\n  orig: 120, 129\n  offset: 0, 0\n  index: -1\nsao2/sao2_18\n  rotate: false\n  xy: 1423, 189\n  size: 120, 129\n  orig: 120, 129\n  offset: 0, 0\n  index: -1\nsao2/sao2_20\n  rotate: false\n  xy: 1545, 189\n  size: 120, 129\n  orig: 120, 129\n  offset: 0, 0\n  index: -1\nsao2/sao2_21\n  rotate: false\n  xy: 1667, 192\n  size: 120, 129\n  orig: 120, 129\n  offset: 0, 0\n  index: -1\nsao2/sao2_23\n  rotate: false\n  xy: 1753, 381\n  size: 120, 129\n  orig: 120, 129\n  offset: 0, 0\n  index: -1\nsao2/sao2_25\n  rotate: false\n  xy: 1681, 61\n  size: 120, 129\n  orig: 120, 129\n  offset: 0, 0\n  index: -1\nsao2/sao2_27\n  rotate: false\n  xy: 1789, 250\n  size: 120, 129\n  orig: 120, 129\n  offset: 0, 0\n  index: -1\nsao2/sao2_28\n  rotate: false\n  xy: 1875, 381\n  size: 120, 129\n  orig: 120, 129\n  offset: 0, 0\n  index: -1\nsao2/sao2_30\n  rotate: false\n  xy: 1911, 250\n  size: 120, 129\n  orig: 120, 129\n  offset: 0, 0\n  index: -1\ntheme211_map_4\n  rotate: false\n  xy: 2, 169\n  size: 283, 341\n  orig: 283, 341\n  offset: 0, 0\n  index: -1\n","textures":[{"__uuid__":"dfy7zk2WBOmILFN1RfET9V"}],"textureNames":["jiedian2.png"]}