{"__type__":"sp.SkeletonData","_name":"spine","_skeletonJson":{"skeleton":{"hash":"UOihtQx3W6jDNwWiLUqlOCo2k8Y","spine":"3.6.53","width":761.17,"height":424.43,"images":"../texiao/"},"bones":[{"name":"root"},{"name":"1","parent":"root"},{"name":"lunzhouyinfu_1","parent":"1","x":-62.25,"y":5.9,"scaleX":1.523,"scaleY":-1.42},{"name":"lunzhouyinfu_2","parent":"1","x":65.73,"y":5.9,"scaleX":1.523,"scaleY":1.424},{"name":"lunzhouyinfu_3","parent":"1","x":192.82,"y":5.9,"scaleX":1.523,"scaleY":-1.45},{"name":"lunzhouyinfu_4","parent":"1","x":319.02,"y":5.9,"scaleX":1.523,"scaleY":1.424},{"name":"lunzhouyinfu_5","parent":"1","x":-189.34,"y":5.9,"scaleX":1.523,"scaleY":1.424},{"name":"lunzhouyinfu_6","parent":"1","x":-329.85,"y":5.9,"scaleX":1.523,"scaleY":1.424},{"name":"lunzhouyinfu_7","parent":"1","rotation":90,"x":58.57,"y":166.11,"scaleX":1.441,"scaleY":2.509},{"name":"lunzhouyinfu_8","parent":"1","rotation":90,"x":58.57,"y":-151.62,"scaleX":1.441,"scaleY":2.509},{"name":"lunzhouyinfu_9","parent":"1","rotation":90,"x":-265.13,"y":-136.57,"scaleX":1.006,"scaleY":0.654},{"name":"lunzhouyinfu_10","parent":"1","rotation":90,"x":-265.13,"y":148.19,"scaleX":1.006,"scaleY":0.654},{"name":"menghei","parent":"root","scaleX":4,"scaleY":4},{"name":"menghei_1","parent":"root","y":24.65,"scaleX":2,"scaleY":2},{"name":"骨骼","parent":"root"}],"slots":[{"name":"free1","bone":"骨骼"},{"name":"menghei","bone":"menghei","attachment":"menghei"},{"name":"menghei/menghei_1","bone":"menghei_1","attachment":"menghei/menghei_10"},{"name":"lunzhouyinfu/lunzhouyinfu_9","bone":"lunzhouyinfu_9","attachment":"lunzhouyinfu/lunzhouyinfu_9"},{"name":"lunzhouyinfu/lunzhouyinfu_10","bone":"lunzhouyinfu_10","attachment":"lunzhouyinfu/lunzhouyinfu_9"},{"name":"lunzhouyinfu/lunzhouyinfu_7","bone":"lunzhouyinfu_7","attachment":"lunzhouyinfu/lunzhouyinfu_9"},{"name":"lunzhouyinfu/lunzhouyinfu_8","bone":"lunzhouyinfu_8","attachment":"lunzhouyinfu/lunzhouyinfu_9"},{"name":"lunzhouyinfu/lunzhouyinfu_1","bone":"lunzhouyinfu_1","attachment":"lunzhouyinfu/lunzhouyinfu_9"},{"name":"lunzhouyinfu/lunzhouyinfu_2","bone":"lunzhouyinfu_2","attachment":"lunzhouyinfu/lunzhouyinfu_9"},{"name":"lunzhouyinfu/lunzhouyinfu_3","bone":"lunzhouyinfu_3","attachment":"lunzhouyinfu/lunzhouyinfu_9"},{"name":"lunzhouyinfu/lunzhouyinfu_4","bone":"lunzhouyinfu_4","attachment":"lunzhouyinfu/lunzhouyinfu_9"},{"name":"lunzhouyinfu/lunzhouyinfu_5","bone":"lunzhouyinfu_5","attachment":"lunzhouyinfu/lunzhouyinfu_9"},{"name":"lunzhouyinfu/lunzhouyinfu_6","bone":"lunzhouyinfu_6","attachment":"lunzhouyinfu/lunzhouyinfu_9"}],"skins":{"default":{"lunzhouyinfu/lunzhouyinfu_1":{"lunzhouyinfu/lunzhouyinfu_1":{"width":71,"height":254},"lunzhouyinfu/lunzhouyinfu_2":{"width":71,"height":254},"lunzhouyinfu/lunzhouyinfu_3":{"width":71,"height":254},"lunzhouyinfu/lunzhouyinfu_4":{"width":71,"height":254},"lunzhouyinfu/lunzhouyinfu_5":{"width":71,"height":254},"lunzhouyinfu/lunzhouyinfu_6":{"width":71,"height":254},"lunzhouyinfu/lunzhouyinfu_7":{"width":71,"height":254},"lunzhouyinfu/lunzhouyinfu_8":{"width":71,"height":254},"lunzhouyinfu/lunzhouyinfu_9":{"width":71,"height":254},"lunzhouyinfu/lunzhouyinfu_10":{"width":71,"height":254},"lunzhouyinfu/lunzhouyinfu_11":{"width":71,"height":254},"lunzhouyinfu/lunzhouyinfu_12":{"width":71,"height":254},"lunzhouyinfu/lunzhouyinfu_13":{"width":71,"height":254},"lunzhouyinfu/lunzhouyinfu_14":{"width":71,"height":254},"lunzhouyinfu/lunzhouyinfu_15":{"width":71,"height":254},"lunzhouyinfu/lunzhouyinfu_16":{"width":71,"height":254},"lunzhouyinfu/lunzhouyinfu_17":{"width":71,"height":254},"lunzhouyinfu/lunzhouyinfu_18":{"width":71,"height":254},"lunzhouyinfu/lunzhouyinfu_19":{"width":71,"height":254},"lunzhouyinfu/lunzhouyinfu_20":{"width":71,"height":254},"lunzhouyinfu/lunzhouyinfu_21":{"width":71,"height":254},"lunzhouyinfu/lunzhouyinfu_22":{"width":71,"height":254},"lunzhouyinfu/lunzhouyinfu_23":{"width":71,"height":254},"lunzhouyinfu/lunzhouyinfu_24":{"width":71,"height":254},"lunzhouyinfu/lunzhouyinfu_25":{"width":71,"height":254},"lunzhouyinfu/lunzhouyinfu_26":{"width":71,"height":254},"lunzhouyinfu/lunzhouyinfu_27":{"width":71,"height":254},"lunzhouyinfu/lunzhouyinfu_28":{"width":71,"height":254},"lunzhouyinfu/lunzhouyinfu_29":{"width":71,"height":254},"lunzhouyinfu/lunzhouyinfu_30":{"width":71,"height":254}},"lunzhouyinfu/lunzhouyinfu_10":{"lunzhouyinfu/lunzhouyinfu_1":{"width":71,"height":254},"lunzhouyinfu/lunzhouyinfu_2":{"width":71,"height":254},"lunzhouyinfu/lunzhouyinfu_3":{"width":71,"height":254},"lunzhouyinfu/lunzhouyinfu_4":{"width":71,"height":254},"lunzhouyinfu/lunzhouyinfu_5":{"width":71,"height":254},"lunzhouyinfu/lunzhouyinfu_6":{"width":71,"height":254},"lunzhouyinfu/lunzhouyinfu_7":{"width":71,"height":254},"lunzhouyinfu/lunzhouyinfu_8":{"width":71,"height":254},"lunzhouyinfu/lunzhouyinfu_9":{"width":71,"height":254},"lunzhouyinfu/lunzhouyinfu_10":{"width":71,"height":254},"lunzhouyinfu/lunzhouyinfu_11":{"width":71,"height":254},"lunzhouyinfu/lunzhouyinfu_12":{"width":71,"height":254},"lunzhouyinfu/lunzhouyinfu_13":{"width":71,"height":254},"lunzhouyinfu/lunzhouyinfu_14":{"width":71,"height":254},"lunzhouyinfu/lunzhouyinfu_15":{"width":71,"height":254},"lunzhouyinfu/lunzhouyinfu_16":{"width":71,"height":254},"lunzhouyinfu/lunzhouyinfu_17":{"width":71,"height":254},"lunzhouyinfu/lunzhouyinfu_18":{"width":71,"height":254},"lunzhouyinfu/lunzhouyinfu_19":{"width":71,"height":254},"lunzhouyinfu/lunzhouyinfu_20":{"width":71,"height":254},"lunzhouyinfu/lunzhouyinfu_21":{"width":71,"height":254},"lunzhouyinfu/lunzhouyinfu_22":{"width":71,"height":254},"lunzhouyinfu/lunzhouyinfu_23":{"width":71,"height":254},"lunzhouyinfu/lunzhouyinfu_24":{"width":71,"height":254},"lunzhouyinfu/lunzhouyinfu_25":{"width":71,"height":254},"lunzhouyinfu/lunzhouyinfu_26":{"width":71,"height":254},"lunzhouyinfu/lunzhouyinfu_27":{"width":71,"height":254},"lunzhouyinfu/lunzhouyinfu_28":{"width":71,"height":254},"lunzhouyinfu/lunzhouyinfu_29":{"width":71,"height":254},"lunzhouyinfu/lunzhouyinfu_30":{"width":71,"height":254}},"lunzhouyinfu/lunzhouyinfu_2":{"lunzhouyinfu/lunzhouyinfu_1":{"width":71,"height":254},"lunzhouyinfu/lunzhouyinfu_2":{"width":71,"height":254},"lunzhouyinfu/lunzhouyinfu_3":{"width":71,"height":254},"lunzhouyinfu/lunzhouyinfu_4":{"width":71,"height":254},"lunzhouyinfu/lunzhouyinfu_5":{"width":71,"height":254},"lunzhouyinfu/lunzhouyinfu_6":{"width":71,"height":254},"lunzhouyinfu/lunzhouyinfu_7":{"width":71,"height":254},"lunzhouyinfu/lunzhouyinfu_8":{"width":71,"height":254},"lunzhouyinfu/lunzhouyinfu_9":{"width":71,"height":254},"lunzhouyinfu/lunzhouyinfu_10":{"width":71,"height":254},"lunzhouyinfu/lunzhouyinfu_11":{"width":71,"height":254},"lunzhouyinfu/lunzhouyinfu_12":{"width":71,"height":254},"lunzhouyinfu/lunzhouyinfu_13":{"width":71,"height":254},"lunzhouyinfu/lunzhouyinfu_14":{"width":71,"height":254},"lunzhouyinfu/lunzhouyinfu_15":{"width":71,"height":254},"lunzhouyinfu/lunzhouyinfu_16":{"width":71,"height":254},"lunzhouyinfu/lunzhouyinfu_17":{"width":71,"height":254},"lunzhouyinfu/lunzhouyinfu_18":{"width":71,"height":254},"lunzhouyinfu/lunzhouyinfu_19":{"width":71,"height":254},"lunzhouyinfu/lunzhouyinfu_20":{"width":71,"height":254},"lunzhouyinfu/lunzhouyinfu_21":{"width":71,"height":254},"lunzhouyinfu/lunzhouyinfu_22":{"width":71,"height":254},"lunzhouyinfu/lunzhouyinfu_23":{"width":71,"height":254},"lunzhouyinfu/lunzhouyinfu_24":{"width":71,"height":254},"lunzhouyinfu/lunzhouyinfu_25":{"width":71,"height":254},"lunzhouyinfu/lunzhouyinfu_26":{"width":71,"height":254},"lunzhouyinfu/lunzhouyinfu_27":{"width":71,"height":254},"lunzhouyinfu/lunzhouyinfu_28":{"width":71,"height":254},"lunzhouyinfu/lunzhouyinfu_29":{"width":71,"height":254},"lunzhouyinfu/lunzhouyinfu_30":{"width":71,"height":254}},"lunzhouyinfu/lunzhouyinfu_3":{"lunzhouyinfu/lunzhouyinfu_1":{"width":71,"height":254},"lunzhouyinfu/lunzhouyinfu_2":{"width":71,"height":254},"lunzhouyinfu/lunzhouyinfu_3":{"width":71,"height":254},"lunzhouyinfu/lunzhouyinfu_4":{"width":71,"height":254},"lunzhouyinfu/lunzhouyinfu_5":{"width":71,"height":254},"lunzhouyinfu/lunzhouyinfu_6":{"width":71,"height":254},"lunzhouyinfu/lunzhouyinfu_7":{"width":71,"height":254},"lunzhouyinfu/lunzhouyinfu_8":{"width":71,"height":254},"lunzhouyinfu/lunzhouyinfu_9":{"width":71,"height":254},"lunzhouyinfu/lunzhouyinfu_10":{"width":71,"height":254},"lunzhouyinfu/lunzhouyinfu_11":{"width":71,"height":254},"lunzhouyinfu/lunzhouyinfu_12":{"width":71,"height":254},"lunzhouyinfu/lunzhouyinfu_13":{"width":71,"height":254},"lunzhouyinfu/lunzhouyinfu_14":{"width":71,"height":254},"lunzhouyinfu/lunzhouyinfu_15":{"width":71,"height":254},"lunzhouyinfu/lunzhouyinfu_16":{"width":71,"height":254},"lunzhouyinfu/lunzhouyinfu_17":{"width":71,"height":254},"lunzhouyinfu/lunzhouyinfu_18":{"width":71,"height":254},"lunzhouyinfu/lunzhouyinfu_19":{"width":71,"height":254},"lunzhouyinfu/lunzhouyinfu_20":{"width":71,"height":254},"lunzhouyinfu/lunzhouyinfu_21":{"width":71,"height":254},"lunzhouyinfu/lunzhouyinfu_22":{"width":71,"height":254},"lunzhouyinfu/lunzhouyinfu_23":{"width":71,"height":254},"lunzhouyinfu/lunzhouyinfu_24":{"width":71,"height":254},"lunzhouyinfu/lunzhouyinfu_25":{"width":71,"height":254},"lunzhouyinfu/lunzhouyinfu_26":{"width":71,"height":254},"lunzhouyinfu/lunzhouyinfu_27":{"width":71,"height":254},"lunzhouyinfu/lunzhouyinfu_28":{"width":71,"height":254},"lunzhouyinfu/lunzhouyinfu_29":{"width":71,"height":254},"lunzhouyinfu/lunzhouyinfu_30":{"width":71,"height":254}},"lunzhouyinfu/lunzhouyinfu_4":{"lunzhouyinfu/lunzhouyinfu_1":{"width":71,"height":254},"lunzhouyinfu/lunzhouyinfu_2":{"width":71,"height":254},"lunzhouyinfu/lunzhouyinfu_3":{"width":71,"height":254},"lunzhouyinfu/lunzhouyinfu_4":{"width":71,"height":254},"lunzhouyinfu/lunzhouyinfu_5":{"width":71,"height":254},"lunzhouyinfu/lunzhouyinfu_6":{"width":71,"height":254},"lunzhouyinfu/lunzhouyinfu_7":{"width":71,"height":254},"lunzhouyinfu/lunzhouyinfu_8":{"width":71,"height":254},"lunzhouyinfu/lunzhouyinfu_9":{"width":71,"height":254},"lunzhouyinfu/lunzhouyinfu_10":{"width":71,"height":254},"lunzhouyinfu/lunzhouyinfu_11":{"width":71,"height":254},"lunzhouyinfu/lunzhouyinfu_12":{"width":71,"height":254},"lunzhouyinfu/lunzhouyinfu_13":{"width":71,"height":254},"lunzhouyinfu/lunzhouyinfu_14":{"width":71,"height":254},"lunzhouyinfu/lunzhouyinfu_15":{"width":71,"height":254},"lunzhouyinfu/lunzhouyinfu_16":{"width":71,"height":254},"lunzhouyinfu/lunzhouyinfu_17":{"width":71,"height":254},"lunzhouyinfu/lunzhouyinfu_18":{"width":71,"height":254},"lunzhouyinfu/lunzhouyinfu_19":{"width":71,"height":254},"lunzhouyinfu/lunzhouyinfu_20":{"width":71,"height":254},"lunzhouyinfu/lunzhouyinfu_21":{"width":71,"height":254},"lunzhouyinfu/lunzhouyinfu_22":{"width":71,"height":254},"lunzhouyinfu/lunzhouyinfu_23":{"width":71,"height":254},"lunzhouyinfu/lunzhouyinfu_24":{"width":71,"height":254},"lunzhouyinfu/lunzhouyinfu_25":{"width":71,"height":254},"lunzhouyinfu/lunzhouyinfu_26":{"width":71,"height":254},"lunzhouyinfu/lunzhouyinfu_27":{"width":71,"height":254},"lunzhouyinfu/lunzhouyinfu_28":{"width":71,"height":254},"lunzhouyinfu/lunzhouyinfu_29":{"width":71,"height":254},"lunzhouyinfu/lunzhouyinfu_30":{"width":71,"height":254}},"lunzhouyinfu/lunzhouyinfu_5":{"lunzhouyinfu/lunzhouyinfu_1":{"width":71,"height":254},"lunzhouyinfu/lunzhouyinfu_2":{"width":71,"height":254},"lunzhouyinfu/lunzhouyinfu_3":{"width":71,"height":254},"lunzhouyinfu/lunzhouyinfu_4":{"width":71,"height":254},"lunzhouyinfu/lunzhouyinfu_5":{"width":71,"height":254},"lunzhouyinfu/lunzhouyinfu_6":{"width":71,"height":254},"lunzhouyinfu/lunzhouyinfu_7":{"width":71,"height":254},"lunzhouyinfu/lunzhouyinfu_8":{"width":71,"height":254},"lunzhouyinfu/lunzhouyinfu_9":{"width":71,"height":254},"lunzhouyinfu/lunzhouyinfu_10":{"width":71,"height":254},"lunzhouyinfu/lunzhouyinfu_11":{"width":71,"height":254},"lunzhouyinfu/lunzhouyinfu_12":{"width":71,"height":254},"lunzhouyinfu/lunzhouyinfu_13":{"width":71,"height":254},"lunzhouyinfu/lunzhouyinfu_14":{"width":71,"height":254},"lunzhouyinfu/lunzhouyinfu_15":{"width":71,"height":254},"lunzhouyinfu/lunzhouyinfu_16":{"width":71,"height":254},"lunzhouyinfu/lunzhouyinfu_17":{"width":71,"height":254},"lunzhouyinfu/lunzhouyinfu_18":{"width":71,"height":254},"lunzhouyinfu/lunzhouyinfu_19":{"width":71,"height":254},"lunzhouyinfu/lunzhouyinfu_20":{"width":71,"height":254},"lunzhouyinfu/lunzhouyinfu_21":{"width":71,"height":254},"lunzhouyinfu/lunzhouyinfu_22":{"width":71,"height":254},"lunzhouyinfu/lunzhouyinfu_23":{"width":71,"height":254},"lunzhouyinfu/lunzhouyinfu_24":{"width":71,"height":254},"lunzhouyinfu/lunzhouyinfu_25":{"width":71,"height":254},"lunzhouyinfu/lunzhouyinfu_26":{"width":71,"height":254},"lunzhouyinfu/lunzhouyinfu_27":{"width":71,"height":254},"lunzhouyinfu/lunzhouyinfu_28":{"width":71,"height":254},"lunzhouyinfu/lunzhouyinfu_29":{"width":71,"height":254},"lunzhouyinfu/lunzhouyinfu_30":{"width":71,"height":254}},"lunzhouyinfu/lunzhouyinfu_6":{"lunzhouyinfu/lunzhouyinfu_1":{"width":71,"height":254},"lunzhouyinfu/lunzhouyinfu_2":{"width":71,"height":254},"lunzhouyinfu/lunzhouyinfu_3":{"width":71,"height":254},"lunzhouyinfu/lunzhouyinfu_4":{"width":71,"height":254},"lunzhouyinfu/lunzhouyinfu_5":{"width":71,"height":254},"lunzhouyinfu/lunzhouyinfu_6":{"width":71,"height":254},"lunzhouyinfu/lunzhouyinfu_7":{"width":71,"height":254},"lunzhouyinfu/lunzhouyinfu_8":{"width":71,"height":254},"lunzhouyinfu/lunzhouyinfu_9":{"width":71,"height":254},"lunzhouyinfu/lunzhouyinfu_10":{"width":71,"height":254},"lunzhouyinfu/lunzhouyinfu_11":{"width":71,"height":254},"lunzhouyinfu/lunzhouyinfu_12":{"width":71,"height":254},"lunzhouyinfu/lunzhouyinfu_13":{"width":71,"height":254},"lunzhouyinfu/lunzhouyinfu_14":{"width":71,"height":254},"lunzhouyinfu/lunzhouyinfu_15":{"width":71,"height":254},"lunzhouyinfu/lunzhouyinfu_16":{"width":71,"height":254},"lunzhouyinfu/lunzhouyinfu_17":{"width":71,"height":254},"lunzhouyinfu/lunzhouyinfu_18":{"width":71,"height":254},"lunzhouyinfu/lunzhouyinfu_19":{"width":71,"height":254},"lunzhouyinfu/lunzhouyinfu_20":{"width":71,"height":254},"lunzhouyinfu/lunzhouyinfu_21":{"width":71,"height":254},"lunzhouyinfu/lunzhouyinfu_22":{"width":71,"height":254},"lunzhouyinfu/lunzhouyinfu_23":{"width":71,"height":254},"lunzhouyinfu/lunzhouyinfu_24":{"width":71,"height":254},"lunzhouyinfu/lunzhouyinfu_25":{"width":71,"height":254},"lunzhouyinfu/lunzhouyinfu_26":{"width":71,"height":254},"lunzhouyinfu/lunzhouyinfu_27":{"width":71,"height":254},"lunzhouyinfu/lunzhouyinfu_28":{"width":71,"height":254},"lunzhouyinfu/lunzhouyinfu_29":{"width":71,"height":254},"lunzhouyinfu/lunzhouyinfu_30":{"width":71,"height":254}},"lunzhouyinfu/lunzhouyinfu_7":{"lunzhouyinfu/lunzhouyinfu_1":{"width":71,"height":254},"lunzhouyinfu/lunzhouyinfu_2":{"width":71,"height":254},"lunzhouyinfu/lunzhouyinfu_3":{"width":71,"height":254},"lunzhouyinfu/lunzhouyinfu_4":{"width":71,"height":254},"lunzhouyinfu/lunzhouyinfu_5":{"width":71,"height":254},"lunzhouyinfu/lunzhouyinfu_6":{"width":71,"height":254},"lunzhouyinfu/lunzhouyinfu_7":{"width":71,"height":254},"lunzhouyinfu/lunzhouyinfu_8":{"width":71,"height":254},"lunzhouyinfu/lunzhouyinfu_9":{"width":71,"height":254},"lunzhouyinfu/lunzhouyinfu_10":{"width":71,"height":254},"lunzhouyinfu/lunzhouyinfu_11":{"width":71,"height":254},"lunzhouyinfu/lunzhouyinfu_12":{"width":71,"height":254},"lunzhouyinfu/lunzhouyinfu_13":{"width":71,"height":254},"lunzhouyinfu/lunzhouyinfu_14":{"width":71,"height":254},"lunzhouyinfu/lunzhouyinfu_15":{"width":71,"height":254},"lunzhouyinfu/lunzhouyinfu_16":{"width":71,"height":254},"lunzhouyinfu/lunzhouyinfu_17":{"width":71,"height":254},"lunzhouyinfu/lunzhouyinfu_18":{"width":71,"height":254},"lunzhouyinfu/lunzhouyinfu_19":{"width":71,"height":254},"lunzhouyinfu/lunzhouyinfu_20":{"width":71,"height":254},"lunzhouyinfu/lunzhouyinfu_21":{"width":71,"height":254},"lunzhouyinfu/lunzhouyinfu_22":{"width":71,"height":254},"lunzhouyinfu/lunzhouyinfu_23":{"width":71,"height":254},"lunzhouyinfu/lunzhouyinfu_24":{"width":71,"height":254},"lunzhouyinfu/lunzhouyinfu_25":{"width":71,"height":254},"lunzhouyinfu/lunzhouyinfu_26":{"width":71,"height":254},"lunzhouyinfu/lunzhouyinfu_27":{"width":71,"height":254},"lunzhouyinfu/lunzhouyinfu_28":{"width":71,"height":254},"lunzhouyinfu/lunzhouyinfu_29":{"width":71,"height":254},"lunzhouyinfu/lunzhouyinfu_30":{"width":71,"height":254}},"lunzhouyinfu/lunzhouyinfu_8":{"lunzhouyinfu/lunzhouyinfu_1":{"width":71,"height":254},"lunzhouyinfu/lunzhouyinfu_2":{"width":71,"height":254},"lunzhouyinfu/lunzhouyinfu_3":{"width":71,"height":254},"lunzhouyinfu/lunzhouyinfu_4":{"width":71,"height":254},"lunzhouyinfu/lunzhouyinfu_5":{"width":71,"height":254},"lunzhouyinfu/lunzhouyinfu_6":{"width":71,"height":254},"lunzhouyinfu/lunzhouyinfu_7":{"width":71,"height":254},"lunzhouyinfu/lunzhouyinfu_8":{"width":71,"height":254},"lunzhouyinfu/lunzhouyinfu_9":{"width":71,"height":254},"lunzhouyinfu/lunzhouyinfu_10":{"width":71,"height":254},"lunzhouyinfu/lunzhouyinfu_11":{"width":71,"height":254},"lunzhouyinfu/lunzhouyinfu_12":{"width":71,"height":254},"lunzhouyinfu/lunzhouyinfu_13":{"width":71,"height":254},"lunzhouyinfu/lunzhouyinfu_14":{"width":71,"height":254},"lunzhouyinfu/lunzhouyinfu_15":{"width":71,"height":254},"lunzhouyinfu/lunzhouyinfu_16":{"width":71,"height":254},"lunzhouyinfu/lunzhouyinfu_17":{"width":71,"height":254},"lunzhouyinfu/lunzhouyinfu_18":{"width":71,"height":254},"lunzhouyinfu/lunzhouyinfu_19":{"width":71,"height":254},"lunzhouyinfu/lunzhouyinfu_20":{"width":71,"height":254},"lunzhouyinfu/lunzhouyinfu_21":{"width":71,"height":254},"lunzhouyinfu/lunzhouyinfu_22":{"width":71,"height":254},"lunzhouyinfu/lunzhouyinfu_23":{"width":71,"height":254},"lunzhouyinfu/lunzhouyinfu_24":{"width":71,"height":254},"lunzhouyinfu/lunzhouyinfu_25":{"width":71,"height":254},"lunzhouyinfu/lunzhouyinfu_26":{"width":71,"height":254},"lunzhouyinfu/lunzhouyinfu_27":{"width":71,"height":254},"lunzhouyinfu/lunzhouyinfu_28":{"width":71,"height":254},"lunzhouyinfu/lunzhouyinfu_29":{"width":71,"height":254},"lunzhouyinfu/lunzhouyinfu_30":{"width":71,"height":254}},"lunzhouyinfu/lunzhouyinfu_9":{"lunzhouyinfu/lunzhouyinfu_1":{"width":71,"height":254},"lunzhouyinfu/lunzhouyinfu_2":{"width":71,"height":254},"lunzhouyinfu/lunzhouyinfu_3":{"width":71,"height":254},"lunzhouyinfu/lunzhouyinfu_4":{"width":71,"height":254},"lunzhouyinfu/lunzhouyinfu_5":{"width":71,"height":254},"lunzhouyinfu/lunzhouyinfu_6":{"width":71,"height":254},"lunzhouyinfu/lunzhouyinfu_7":{"width":71,"height":254},"lunzhouyinfu/lunzhouyinfu_8":{"width":71,"height":254},"lunzhouyinfu/lunzhouyinfu_9":{"width":71,"height":254},"lunzhouyinfu/lunzhouyinfu_10":{"width":71,"height":254},"lunzhouyinfu/lunzhouyinfu_11":{"width":71,"height":254},"lunzhouyinfu/lunzhouyinfu_12":{"width":71,"height":254},"lunzhouyinfu/lunzhouyinfu_13":{"width":71,"height":254},"lunzhouyinfu/lunzhouyinfu_14":{"width":71,"height":254},"lunzhouyinfu/lunzhouyinfu_15":{"width":71,"height":254},"lunzhouyinfu/lunzhouyinfu_16":{"width":71,"height":254},"lunzhouyinfu/lunzhouyinfu_17":{"width":71,"height":254},"lunzhouyinfu/lunzhouyinfu_18":{"width":71,"height":254},"lunzhouyinfu/lunzhouyinfu_19":{"width":71,"height":254},"lunzhouyinfu/lunzhouyinfu_20":{"width":71,"height":254},"lunzhouyinfu/lunzhouyinfu_21":{"width":71,"height":254},"lunzhouyinfu/lunzhouyinfu_22":{"width":71,"height":254},"lunzhouyinfu/lunzhouyinfu_23":{"width":71,"height":254},"lunzhouyinfu/lunzhouyinfu_24":{"width":71,"height":254},"lunzhouyinfu/lunzhouyinfu_25":{"width":71,"height":254},"lunzhouyinfu/lunzhouyinfu_26":{"width":71,"height":254},"lunzhouyinfu/lunzhouyinfu_27":{"width":71,"height":254},"lunzhouyinfu/lunzhouyinfu_28":{"width":71,"height":254},"lunzhouyinfu/lunzhouyinfu_29":{"width":71,"height":254},"lunzhouyinfu/lunzhouyinfu_30":{"width":71,"height":254}},"menghei":{"menghei":{"width":159,"height":76}},"menghei/menghei_1":{"menghei/menghei_1":{"width":363,"height":197},"menghei/menghei_2":{"width":363,"height":197},"menghei/menghei_3":{"width":363,"height":197},"menghei/menghei_4":{"width":363,"height":197},"menghei/menghei_5":{"width":363,"height":197},"menghei/menghei_6":{"width":363,"height":197},"menghei/menghei_7":{"width":363,"height":197},"menghei/menghei_8":{"width":363,"height":197},"menghei/menghei_9":{"width":363,"height":197},"menghei/menghei_10":{"width":363,"height":197},"menghei/menghei_11":{"width":363,"height":197},"menghei/menghei_12":{"width":363,"height":197},"menghei/menghei_13":{"width":363,"height":197},"menghei/menghei_14":{"width":363,"height":197},"menghei/menghei_15":{"width":363,"height":197},"menghei/menghei_16":{"width":363,"height":197},"menghei/menghei_17":{"width":363,"height":197},"menghei/menghei_18":{"width":363,"height":197},"menghei/menghei_19":{"width":363,"height":197},"menghei/menghei_20":{"width":363,"height":197},"menghei/menghei_21":{"width":363,"height":197},"menghei/menghei_22":{"width":363,"height":197},"menghei/menghei_23":{"width":363,"height":197},"menghei/menghei_24":{"width":363,"height":197},"menghei/menghei_25":{"width":363,"height":197},"menghei/menghei_26":{"width":363,"height":197},"menghei/menghei_27":{"width":363,"height":197},"menghei/menghei_28":{"width":363,"height":197},"menghei/menghei_29":{"width":363,"height":197},"menghei/menghei_30":{"width":363,"height":197},"menghei/menghei_31":{"width":363,"height":197},"menghei/menghei_32":{"width":363,"height":197},"menghei/menghei_33":{"width":363,"height":197},"menghei/menghei_34":{"width":363,"height":197},"menghei/menghei_35":{"width":363,"height":197},"menghei/menghei_36":{"width":363,"height":197},"menghei/menghei_37":{"width":363,"height":197},"menghei/menghei_38":{"width":363,"height":197},"menghei/menghei_39":{"width":363,"height":197}}}},"animations":{"animation1":{"slots":{"lunzhouyinfu/lunzhouyinfu_1":{"color":[{"time":0,"color":"ffffff00"},{"time":0.5,"color":"ffffffff"}],"attachment":[{"time":0,"name":"lunzhouyinfu/lunzhouyinfu_16"},{"time":0.0333,"name":"lunzhouyinfu/lunzhouyinfu_17"},{"time":0.0667,"name":"lunzhouyinfu/lunzhouyinfu_18"},{"time":0.1,"name":"lunzhouyinfu/lunzhouyinfu_19"},{"time":0.1333,"name":"lunzhouyinfu/lunzhouyinfu_20"},{"time":0.1667,"name":"lunzhouyinfu/lunzhouyinfu_21"},{"time":0.2,"name":"lunzhouyinfu/lunzhouyinfu_22"},{"time":0.2333,"name":"lunzhouyinfu/lunzhouyinfu_23"},{"time":0.2667,"name":"lunzhouyinfu/lunzhouyinfu_24"},{"time":0.3,"name":"lunzhouyinfu/lunzhouyinfu_25"},{"time":0.3333,"name":"lunzhouyinfu/lunzhouyinfu_26"},{"time":0.3667,"name":"lunzhouyinfu/lunzhouyinfu_27"},{"time":0.4,"name":"lunzhouyinfu/lunzhouyinfu_28"},{"time":0.4333,"name":"lunzhouyinfu/lunzhouyinfu_29"},{"time":0.4667,"name":"lunzhouyinfu/lunzhouyinfu_30"},{"time":0.5,"name":"lunzhouyinfu/lunzhouyinfu_1"}]},"lunzhouyinfu/lunzhouyinfu_2":{"color":[{"time":0,"color":"ffffff00"},{"time":0.5,"color":"ffffffff"}],"attachment":[{"time":0,"name":"lunzhouyinfu/lunzhouyinfu_16"},{"time":0.0333,"name":"lunzhouyinfu/lunzhouyinfu_17"},{"time":0.0667,"name":"lunzhouyinfu/lunzhouyinfu_18"},{"time":0.1,"name":"lunzhouyinfu/lunzhouyinfu_19"},{"time":0.1333,"name":"lunzhouyinfu/lunzhouyinfu_20"},{"time":0.1667,"name":"lunzhouyinfu/lunzhouyinfu_21"},{"time":0.2,"name":"lunzhouyinfu/lunzhouyinfu_22"},{"time":0.2333,"name":"lunzhouyinfu/lunzhouyinfu_23"},{"time":0.2667,"name":"lunzhouyinfu/lunzhouyinfu_24"},{"time":0.3,"name":"lunzhouyinfu/lunzhouyinfu_25"},{"time":0.3333,"name":"lunzhouyinfu/lunzhouyinfu_26"},{"time":0.3667,"name":"lunzhouyinfu/lunzhouyinfu_27"},{"time":0.4,"name":"lunzhouyinfu/lunzhouyinfu_28"},{"time":0.4333,"name":"lunzhouyinfu/lunzhouyinfu_29"},{"time":0.4667,"name":"lunzhouyinfu/lunzhouyinfu_30"},{"time":0.5,"name":"lunzhouyinfu/lunzhouyinfu_1"}]},"lunzhouyinfu/lunzhouyinfu_3":{"color":[{"time":0,"color":"ffffff00"},{"time":0.5,"color":"ffffffff"}],"attachment":[{"time":0,"name":"lunzhouyinfu/lunzhouyinfu_16"},{"time":0.0333,"name":"lunzhouyinfu/lunzhouyinfu_17"},{"time":0.0667,"name":"lunzhouyinfu/lunzhouyinfu_18"},{"time":0.1,"name":"lunzhouyinfu/lunzhouyinfu_19"},{"time":0.1333,"name":"lunzhouyinfu/lunzhouyinfu_20"},{"time":0.1667,"name":"lunzhouyinfu/lunzhouyinfu_21"},{"time":0.2,"name":"lunzhouyinfu/lunzhouyinfu_22"},{"time":0.2333,"name":"lunzhouyinfu/lunzhouyinfu_23"},{"time":0.2667,"name":"lunzhouyinfu/lunzhouyinfu_24"},{"time":0.3,"name":"lunzhouyinfu/lunzhouyinfu_25"},{"time":0.3333,"name":"lunzhouyinfu/lunzhouyinfu_26"},{"time":0.3667,"name":"lunzhouyinfu/lunzhouyinfu_27"},{"time":0.4,"name":"lunzhouyinfu/lunzhouyinfu_28"},{"time":0.4333,"name":"lunzhouyinfu/lunzhouyinfu_29"},{"time":0.4667,"name":"lunzhouyinfu/lunzhouyinfu_30"},{"time":0.5,"name":"lunzhouyinfu/lunzhouyinfu_1"}]},"lunzhouyinfu/lunzhouyinfu_4":{"color":[{"time":0,"color":"ffffff00"},{"time":0.5,"color":"ffffffff"}],"attachment":[{"time":0,"name":"lunzhouyinfu/lunzhouyinfu_16"},{"time":0.0333,"name":"lunzhouyinfu/lunzhouyinfu_17"},{"time":0.0667,"name":"lunzhouyinfu/lunzhouyinfu_18"},{"time":0.1,"name":"lunzhouyinfu/lunzhouyinfu_19"},{"time":0.1333,"name":"lunzhouyinfu/lunzhouyinfu_20"},{"time":0.1667,"name":"lunzhouyinfu/lunzhouyinfu_21"},{"time":0.2,"name":"lunzhouyinfu/lunzhouyinfu_22"},{"time":0.2333,"name":"lunzhouyinfu/lunzhouyinfu_23"},{"time":0.2667,"name":"lunzhouyinfu/lunzhouyinfu_24"},{"time":0.3,"name":"lunzhouyinfu/lunzhouyinfu_25"},{"time":0.3333,"name":"lunzhouyinfu/lunzhouyinfu_26"},{"time":0.3667,"name":"lunzhouyinfu/lunzhouyinfu_27"},{"time":0.4,"name":"lunzhouyinfu/lunzhouyinfu_28"},{"time":0.4333,"name":"lunzhouyinfu/lunzhouyinfu_29"},{"time":0.4667,"name":"lunzhouyinfu/lunzhouyinfu_30"},{"time":0.5,"name":"lunzhouyinfu/lunzhouyinfu_1"}]},"lunzhouyinfu/lunzhouyinfu_5":{"color":[{"time":0,"color":"ffffff00"},{"time":0.5,"color":"ffffffff"}],"attachment":[{"time":0,"name":"lunzhouyinfu/lunzhouyinfu_16"},{"time":0.0333,"name":"lunzhouyinfu/lunzhouyinfu_17"},{"time":0.0667,"name":"lunzhouyinfu/lunzhouyinfu_18"},{"time":0.1,"name":"lunzhouyinfu/lunzhouyinfu_19"},{"time":0.1333,"name":"lunzhouyinfu/lunzhouyinfu_20"},{"time":0.1667,"name":"lunzhouyinfu/lunzhouyinfu_21"},{"time":0.2,"name":"lunzhouyinfu/lunzhouyinfu_22"},{"time":0.2333,"name":"lunzhouyinfu/lunzhouyinfu_23"},{"time":0.2667,"name":"lunzhouyinfu/lunzhouyinfu_24"},{"time":0.3,"name":"lunzhouyinfu/lunzhouyinfu_25"},{"time":0.3333,"name":"lunzhouyinfu/lunzhouyinfu_26"},{"time":0.3667,"name":"lunzhouyinfu/lunzhouyinfu_27"},{"time":0.4,"name":"lunzhouyinfu/lunzhouyinfu_28"},{"time":0.4333,"name":"lunzhouyinfu/lunzhouyinfu_29"},{"time":0.4667,"name":"lunzhouyinfu/lunzhouyinfu_30"},{"time":0.5,"name":"lunzhouyinfu/lunzhouyinfu_1"}]},"lunzhouyinfu/lunzhouyinfu_6":{"color":[{"time":0,"color":"ffffff00"},{"time":0.5,"color":"ffffffff"}],"attachment":[{"time":0,"name":"lunzhouyinfu/lunzhouyinfu_16"},{"time":0.0333,"name":"lunzhouyinfu/lunzhouyinfu_17"},{"time":0.0667,"name":"lunzhouyinfu/lunzhouyinfu_18"},{"time":0.1,"name":"lunzhouyinfu/lunzhouyinfu_19"},{"time":0.1333,"name":"lunzhouyinfu/lunzhouyinfu_20"},{"time":0.1667,"name":"lunzhouyinfu/lunzhouyinfu_21"},{"time":0.2,"name":"lunzhouyinfu/lunzhouyinfu_22"},{"time":0.2333,"name":"lunzhouyinfu/lunzhouyinfu_23"},{"time":0.2667,"name":"lunzhouyinfu/lunzhouyinfu_24"},{"time":0.3,"name":"lunzhouyinfu/lunzhouyinfu_25"},{"time":0.3333,"name":"lunzhouyinfu/lunzhouyinfu_26"},{"time":0.3667,"name":"lunzhouyinfu/lunzhouyinfu_27"},{"time":0.4,"name":"lunzhouyinfu/lunzhouyinfu_28"},{"time":0.4333,"name":"lunzhouyinfu/lunzhouyinfu_29"},{"time":0.4667,"name":"lunzhouyinfu/lunzhouyinfu_30"},{"time":0.5,"name":"lunzhouyinfu/lunzhouyinfu_1"}]},"lunzhouyinfu/lunzhouyinfu_7":{"color":[{"time":0,"color":"ffffff00"},{"time":0.5,"color":"ffffffff"}],"attachment":[{"time":0,"name":"lunzhouyinfu/lunzhouyinfu_16"},{"time":0.0333,"name":"lunzhouyinfu/lunzhouyinfu_17"},{"time":0.0667,"name":"lunzhouyinfu/lunzhouyinfu_18"},{"time":0.1,"name":"lunzhouyinfu/lunzhouyinfu_19"},{"time":0.1333,"name":"lunzhouyinfu/lunzhouyinfu_20"},{"time":0.1667,"name":"lunzhouyinfu/lunzhouyinfu_21"},{"time":0.2,"name":"lunzhouyinfu/lunzhouyinfu_22"},{"time":0.2333,"name":"lunzhouyinfu/lunzhouyinfu_23"},{"time":0.2667,"name":"lunzhouyinfu/lunzhouyinfu_24"},{"time":0.3,"name":"lunzhouyinfu/lunzhouyinfu_25"},{"time":0.3333,"name":"lunzhouyinfu/lunzhouyinfu_26"},{"time":0.3667,"name":"lunzhouyinfu/lunzhouyinfu_27"},{"time":0.4,"name":"lunzhouyinfu/lunzhouyinfu_28"},{"time":0.4333,"name":"lunzhouyinfu/lunzhouyinfu_29"},{"time":0.4667,"name":"lunzhouyinfu/lunzhouyinfu_30"},{"time":0.5,"name":"lunzhouyinfu/lunzhouyinfu_1"}]},"lunzhouyinfu/lunzhouyinfu_8":{"color":[{"time":0,"color":"ffffff00"},{"time":0.5,"color":"ffffffff"}],"attachment":[{"time":0,"name":"lunzhouyinfu/lunzhouyinfu_16"},{"time":0.0333,"name":"lunzhouyinfu/lunzhouyinfu_17"},{"time":0.0667,"name":"lunzhouyinfu/lunzhouyinfu_18"},{"time":0.1,"name":"lunzhouyinfu/lunzhouyinfu_19"},{"time":0.1333,"name":"lunzhouyinfu/lunzhouyinfu_20"},{"time":0.1667,"name":"lunzhouyinfu/lunzhouyinfu_21"},{"time":0.2,"name":"lunzhouyinfu/lunzhouyinfu_22"},{"time":0.2333,"name":"lunzhouyinfu/lunzhouyinfu_23"},{"time":0.2667,"name":"lunzhouyinfu/lunzhouyinfu_24"},{"time":0.3,"name":"lunzhouyinfu/lunzhouyinfu_25"},{"time":0.3333,"name":"lunzhouyinfu/lunzhouyinfu_26"},{"time":0.3667,"name":"lunzhouyinfu/lunzhouyinfu_27"},{"time":0.4,"name":"lunzhouyinfu/lunzhouyinfu_28"},{"time":0.4333,"name":"lunzhouyinfu/lunzhouyinfu_29"},{"time":0.4667,"name":"lunzhouyinfu/lunzhouyinfu_30"},{"time":0.5,"name":"lunzhouyinfu/lunzhouyinfu_1"}]},"lunzhouyinfu/lunzhouyinfu_9":{"color":[{"time":0,"color":"ffffff00"},{"time":0.5,"color":"ffffffff"}],"attachment":[{"time":0,"name":"lunzhouyinfu/lunzhouyinfu_16"},{"time":0.0333,"name":"lunzhouyinfu/lunzhouyinfu_17"},{"time":0.0667,"name":"lunzhouyinfu/lunzhouyinfu_18"},{"time":0.1,"name":"lunzhouyinfu/lunzhouyinfu_19"},{"time":0.1333,"name":"lunzhouyinfu/lunzhouyinfu_20"},{"time":0.1667,"name":"lunzhouyinfu/lunzhouyinfu_21"},{"time":0.2,"name":"lunzhouyinfu/lunzhouyinfu_22"},{"time":0.2333,"name":"lunzhouyinfu/lunzhouyinfu_23"},{"time":0.2667,"name":"lunzhouyinfu/lunzhouyinfu_24"},{"time":0.3,"name":"lunzhouyinfu/lunzhouyinfu_25"},{"time":0.3333,"name":"lunzhouyinfu/lunzhouyinfu_26"},{"time":0.3667,"name":"lunzhouyinfu/lunzhouyinfu_27"},{"time":0.4,"name":"lunzhouyinfu/lunzhouyinfu_28"},{"time":0.4333,"name":"lunzhouyinfu/lunzhouyinfu_29"},{"time":0.4667,"name":"lunzhouyinfu/lunzhouyinfu_30"},{"time":0.5,"name":"lunzhouyinfu/lunzhouyinfu_1"}]},"lunzhouyinfu/lunzhouyinfu_10":{"color":[{"time":0,"color":"ffffff00"},{"time":0.5,"color":"ffffffff"}],"attachment":[{"time":0,"name":"lunzhouyinfu/lunzhouyinfu_16"},{"time":0.0333,"name":"lunzhouyinfu/lunzhouyinfu_17"},{"time":0.0667,"name":"lunzhouyinfu/lunzhouyinfu_18"},{"time":0.1,"name":"lunzhouyinfu/lunzhouyinfu_19"},{"time":0.1333,"name":"lunzhouyinfu/lunzhouyinfu_20"},{"time":0.1667,"name":"lunzhouyinfu/lunzhouyinfu_21"},{"time":0.2,"name":"lunzhouyinfu/lunzhouyinfu_22"},{"time":0.2333,"name":"lunzhouyinfu/lunzhouyinfu_23"},{"time":0.2667,"name":"lunzhouyinfu/lunzhouyinfu_24"},{"time":0.3,"name":"lunzhouyinfu/lunzhouyinfu_25"},{"time":0.3333,"name":"lunzhouyinfu/lunzhouyinfu_26"},{"time":0.3667,"name":"lunzhouyinfu/lunzhouyinfu_27"},{"time":0.4,"name":"lunzhouyinfu/lunzhouyinfu_28"},{"time":0.4333,"name":"lunzhouyinfu/lunzhouyinfu_29"},{"time":0.4667,"name":"lunzhouyinfu/lunzhouyinfu_30"},{"time":0.5,"name":"lunzhouyinfu/lunzhouyinfu_1"}]},"menghei":{"color":[{"time":0,"color":"ffffff00","curve":[0.25,0,0.75,1]},{"time":0.5,"color":"ffffff73"}]},"menghei/menghei_1":{"attachment":[{"time":0,"name":null}]}}},"animation2":{"slots":{"lunzhouyinfu/lunzhouyinfu_1":{"attachment":[{"time":0,"name":"lunzhouyinfu/lunzhouyinfu_1"},{"time":0.0333,"name":"lunzhouyinfu/lunzhouyinfu_2"},{"time":0.0667,"name":"lunzhouyinfu/lunzhouyinfu_3"},{"time":0.1,"name":"lunzhouyinfu/lunzhouyinfu_4"},{"time":0.1333,"name":"lunzhouyinfu/lunzhouyinfu_5"},{"time":0.1667,"name":"lunzhouyinfu/lunzhouyinfu_6"},{"time":0.2,"name":"lunzhouyinfu/lunzhouyinfu_7"},{"time":0.2333,"name":"lunzhouyinfu/lunzhouyinfu_8"},{"time":0.2667,"name":"lunzhouyinfu/lunzhouyinfu_9"},{"time":0.3,"name":"lunzhouyinfu/lunzhouyinfu_10"},{"time":0.3333,"name":"lunzhouyinfu/lunzhouyinfu_11"},{"time":0.3667,"name":"lunzhouyinfu/lunzhouyinfu_12"},{"time":0.4,"name":"lunzhouyinfu/lunzhouyinfu_13"},{"time":0.4333,"name":"lunzhouyinfu/lunzhouyinfu_14"},{"time":0.4667,"name":"lunzhouyinfu/lunzhouyinfu_15"},{"time":0.5,"name":"lunzhouyinfu/lunzhouyinfu_16"},{"time":0.5333,"name":"lunzhouyinfu/lunzhouyinfu_17"},{"time":0.5667,"name":"lunzhouyinfu/lunzhouyinfu_18"},{"time":0.6,"name":"lunzhouyinfu/lunzhouyinfu_19"},{"time":0.6333,"name":"lunzhouyinfu/lunzhouyinfu_20"},{"time":0.6667,"name":"lunzhouyinfu/lunzhouyinfu_21"},{"time":0.7,"name":"lunzhouyinfu/lunzhouyinfu_22"},{"time":0.7333,"name":"lunzhouyinfu/lunzhouyinfu_23"},{"time":0.7667,"name":"lunzhouyinfu/lunzhouyinfu_24"},{"time":0.8,"name":"lunzhouyinfu/lunzhouyinfu_25"},{"time":0.8333,"name":"lunzhouyinfu/lunzhouyinfu_26"},{"time":0.8667,"name":"lunzhouyinfu/lunzhouyinfu_27"},{"time":0.9,"name":"lunzhouyinfu/lunzhouyinfu_28"},{"time":0.9333,"name":"lunzhouyinfu/lunzhouyinfu_29"},{"time":0.9667,"name":"lunzhouyinfu/lunzhouyinfu_30"},{"time":1,"name":"lunzhouyinfu/lunzhouyinfu_1"}]},"lunzhouyinfu/lunzhouyinfu_2":{"attachment":[{"time":0,"name":"lunzhouyinfu/lunzhouyinfu_1"},{"time":0.0333,"name":"lunzhouyinfu/lunzhouyinfu_2"},{"time":0.0667,"name":"lunzhouyinfu/lunzhouyinfu_3"},{"time":0.1,"name":"lunzhouyinfu/lunzhouyinfu_4"},{"time":0.1333,"name":"lunzhouyinfu/lunzhouyinfu_5"},{"time":0.1667,"name":"lunzhouyinfu/lunzhouyinfu_6"},{"time":0.2,"name":"lunzhouyinfu/lunzhouyinfu_7"},{"time":0.2333,"name":"lunzhouyinfu/lunzhouyinfu_8"},{"time":0.2667,"name":"lunzhouyinfu/lunzhouyinfu_9"},{"time":0.3,"name":"lunzhouyinfu/lunzhouyinfu_10"},{"time":0.3333,"name":"lunzhouyinfu/lunzhouyinfu_11"},{"time":0.3667,"name":"lunzhouyinfu/lunzhouyinfu_12"},{"time":0.4,"name":"lunzhouyinfu/lunzhouyinfu_13"},{"time":0.4333,"name":"lunzhouyinfu/lunzhouyinfu_14"},{"time":0.4667,"name":"lunzhouyinfu/lunzhouyinfu_15"},{"time":0.5,"name":"lunzhouyinfu/lunzhouyinfu_16"},{"time":0.5333,"name":"lunzhouyinfu/lunzhouyinfu_17"},{"time":0.5667,"name":"lunzhouyinfu/lunzhouyinfu_18"},{"time":0.6,"name":"lunzhouyinfu/lunzhouyinfu_19"},{"time":0.6333,"name":"lunzhouyinfu/lunzhouyinfu_20"},{"time":0.6667,"name":"lunzhouyinfu/lunzhouyinfu_21"},{"time":0.7,"name":"lunzhouyinfu/lunzhouyinfu_22"},{"time":0.7333,"name":"lunzhouyinfu/lunzhouyinfu_23"},{"time":0.7667,"name":"lunzhouyinfu/lunzhouyinfu_24"},{"time":0.8,"name":"lunzhouyinfu/lunzhouyinfu_25"},{"time":0.8333,"name":"lunzhouyinfu/lunzhouyinfu_26"},{"time":0.8667,"name":"lunzhouyinfu/lunzhouyinfu_27"},{"time":0.9,"name":"lunzhouyinfu/lunzhouyinfu_28"},{"time":0.9333,"name":"lunzhouyinfu/lunzhouyinfu_29"},{"time":0.9667,"name":"lunzhouyinfu/lunzhouyinfu_30"},{"time":1,"name":"lunzhouyinfu/lunzhouyinfu_1"}]},"lunzhouyinfu/lunzhouyinfu_3":{"attachment":[{"time":0,"name":"lunzhouyinfu/lunzhouyinfu_1"},{"time":0.0333,"name":"lunzhouyinfu/lunzhouyinfu_2"},{"time":0.0667,"name":"lunzhouyinfu/lunzhouyinfu_3"},{"time":0.1,"name":"lunzhouyinfu/lunzhouyinfu_4"},{"time":0.1333,"name":"lunzhouyinfu/lunzhouyinfu_5"},{"time":0.1667,"name":"lunzhouyinfu/lunzhouyinfu_6"},{"time":0.2,"name":"lunzhouyinfu/lunzhouyinfu_7"},{"time":0.2333,"name":"lunzhouyinfu/lunzhouyinfu_8"},{"time":0.2667,"name":"lunzhouyinfu/lunzhouyinfu_9"},{"time":0.3,"name":"lunzhouyinfu/lunzhouyinfu_10"},{"time":0.3333,"name":"lunzhouyinfu/lunzhouyinfu_11"},{"time":0.3667,"name":"lunzhouyinfu/lunzhouyinfu_12"},{"time":0.4,"name":"lunzhouyinfu/lunzhouyinfu_13"},{"time":0.4333,"name":"lunzhouyinfu/lunzhouyinfu_14"},{"time":0.4667,"name":"lunzhouyinfu/lunzhouyinfu_15"},{"time":0.5,"name":"lunzhouyinfu/lunzhouyinfu_16"},{"time":0.5333,"name":"lunzhouyinfu/lunzhouyinfu_17"},{"time":0.5667,"name":"lunzhouyinfu/lunzhouyinfu_18"},{"time":0.6,"name":"lunzhouyinfu/lunzhouyinfu_19"},{"time":0.6333,"name":"lunzhouyinfu/lunzhouyinfu_20"},{"time":0.6667,"name":"lunzhouyinfu/lunzhouyinfu_21"},{"time":0.7,"name":"lunzhouyinfu/lunzhouyinfu_22"},{"time":0.7333,"name":"lunzhouyinfu/lunzhouyinfu_23"},{"time":0.7667,"name":"lunzhouyinfu/lunzhouyinfu_24"},{"time":0.8,"name":"lunzhouyinfu/lunzhouyinfu_25"},{"time":0.8333,"name":"lunzhouyinfu/lunzhouyinfu_26"},{"time":0.8667,"name":"lunzhouyinfu/lunzhouyinfu_27"},{"time":0.9,"name":"lunzhouyinfu/lunzhouyinfu_28"},{"time":0.9333,"name":"lunzhouyinfu/lunzhouyinfu_29"},{"time":0.9667,"name":"lunzhouyinfu/lunzhouyinfu_30"},{"time":1,"name":"lunzhouyinfu/lunzhouyinfu_1"}]},"lunzhouyinfu/lunzhouyinfu_4":{"attachment":[{"time":0,"name":"lunzhouyinfu/lunzhouyinfu_1"},{"time":0.0333,"name":"lunzhouyinfu/lunzhouyinfu_2"},{"time":0.0667,"name":"lunzhouyinfu/lunzhouyinfu_3"},{"time":0.1,"name":"lunzhouyinfu/lunzhouyinfu_4"},{"time":0.1333,"name":"lunzhouyinfu/lunzhouyinfu_5"},{"time":0.1667,"name":"lunzhouyinfu/lunzhouyinfu_6"},{"time":0.2,"name":"lunzhouyinfu/lunzhouyinfu_7"},{"time":0.2333,"name":"lunzhouyinfu/lunzhouyinfu_8"},{"time":0.2667,"name":"lunzhouyinfu/lunzhouyinfu_9"},{"time":0.3,"name":"lunzhouyinfu/lunzhouyinfu_10"},{"time":0.3333,"name":"lunzhouyinfu/lunzhouyinfu_11"},{"time":0.3667,"name":"lunzhouyinfu/lunzhouyinfu_12"},{"time":0.4,"name":"lunzhouyinfu/lunzhouyinfu_13"},{"time":0.4333,"name":"lunzhouyinfu/lunzhouyinfu_14"},{"time":0.4667,"name":"lunzhouyinfu/lunzhouyinfu_15"},{"time":0.5,"name":"lunzhouyinfu/lunzhouyinfu_16"},{"time":0.5333,"name":"lunzhouyinfu/lunzhouyinfu_17"},{"time":0.5667,"name":"lunzhouyinfu/lunzhouyinfu_18"},{"time":0.6,"name":"lunzhouyinfu/lunzhouyinfu_19"},{"time":0.6333,"name":"lunzhouyinfu/lunzhouyinfu_20"},{"time":0.6667,"name":"lunzhouyinfu/lunzhouyinfu_21"},{"time":0.7,"name":"lunzhouyinfu/lunzhouyinfu_22"},{"time":0.7333,"name":"lunzhouyinfu/lunzhouyinfu_23"},{"time":0.7667,"name":"lunzhouyinfu/lunzhouyinfu_24"},{"time":0.8,"name":"lunzhouyinfu/lunzhouyinfu_25"},{"time":0.8333,"name":"lunzhouyinfu/lunzhouyinfu_26"},{"time":0.8667,"name":"lunzhouyinfu/lunzhouyinfu_27"},{"time":0.9,"name":"lunzhouyinfu/lunzhouyinfu_28"},{"time":0.9333,"name":"lunzhouyinfu/lunzhouyinfu_29"},{"time":0.9667,"name":"lunzhouyinfu/lunzhouyinfu_30"},{"time":1,"name":"lunzhouyinfu/lunzhouyinfu_1"}]},"lunzhouyinfu/lunzhouyinfu_5":{"attachment":[{"time":0,"name":"lunzhouyinfu/lunzhouyinfu_1"},{"time":0.0333,"name":"lunzhouyinfu/lunzhouyinfu_2"},{"time":0.0667,"name":"lunzhouyinfu/lunzhouyinfu_3"},{"time":0.1,"name":"lunzhouyinfu/lunzhouyinfu_4"},{"time":0.1333,"name":"lunzhouyinfu/lunzhouyinfu_5"},{"time":0.1667,"name":"lunzhouyinfu/lunzhouyinfu_6"},{"time":0.2,"name":"lunzhouyinfu/lunzhouyinfu_7"},{"time":0.2333,"name":"lunzhouyinfu/lunzhouyinfu_8"},{"time":0.2667,"name":"lunzhouyinfu/lunzhouyinfu_9"},{"time":0.3,"name":"lunzhouyinfu/lunzhouyinfu_10"},{"time":0.3333,"name":"lunzhouyinfu/lunzhouyinfu_11"},{"time":0.3667,"name":"lunzhouyinfu/lunzhouyinfu_12"},{"time":0.4,"name":"lunzhouyinfu/lunzhouyinfu_13"},{"time":0.4333,"name":"lunzhouyinfu/lunzhouyinfu_14"},{"time":0.4667,"name":"lunzhouyinfu/lunzhouyinfu_15"},{"time":0.5,"name":"lunzhouyinfu/lunzhouyinfu_16"},{"time":0.5333,"name":"lunzhouyinfu/lunzhouyinfu_17"},{"time":0.5667,"name":"lunzhouyinfu/lunzhouyinfu_18"},{"time":0.6,"name":"lunzhouyinfu/lunzhouyinfu_19"},{"time":0.6333,"name":"lunzhouyinfu/lunzhouyinfu_20"},{"time":0.6667,"name":"lunzhouyinfu/lunzhouyinfu_21"},{"time":0.7,"name":"lunzhouyinfu/lunzhouyinfu_22"},{"time":0.7333,"name":"lunzhouyinfu/lunzhouyinfu_23"},{"time":0.7667,"name":"lunzhouyinfu/lunzhouyinfu_24"},{"time":0.8,"name":"lunzhouyinfu/lunzhouyinfu_25"},{"time":0.8333,"name":"lunzhouyinfu/lunzhouyinfu_26"},{"time":0.8667,"name":"lunzhouyinfu/lunzhouyinfu_27"},{"time":0.9,"name":"lunzhouyinfu/lunzhouyinfu_28"},{"time":0.9333,"name":"lunzhouyinfu/lunzhouyinfu_29"},{"time":0.9667,"name":"lunzhouyinfu/lunzhouyinfu_30"},{"time":1,"name":"lunzhouyinfu/lunzhouyinfu_1"}]},"lunzhouyinfu/lunzhouyinfu_6":{"attachment":[{"time":0,"name":"lunzhouyinfu/lunzhouyinfu_1"},{"time":0.0333,"name":"lunzhouyinfu/lunzhouyinfu_2"},{"time":0.0667,"name":"lunzhouyinfu/lunzhouyinfu_3"},{"time":0.1,"name":"lunzhouyinfu/lunzhouyinfu_4"},{"time":0.1333,"name":"lunzhouyinfu/lunzhouyinfu_5"},{"time":0.1667,"name":"lunzhouyinfu/lunzhouyinfu_6"},{"time":0.2,"name":"lunzhouyinfu/lunzhouyinfu_7"},{"time":0.2333,"name":"lunzhouyinfu/lunzhouyinfu_8"},{"time":0.2667,"name":"lunzhouyinfu/lunzhouyinfu_9"},{"time":0.3,"name":"lunzhouyinfu/lunzhouyinfu_10"},{"time":0.3333,"name":"lunzhouyinfu/lunzhouyinfu_11"},{"time":0.3667,"name":"lunzhouyinfu/lunzhouyinfu_12"},{"time":0.4,"name":"lunzhouyinfu/lunzhouyinfu_13"},{"time":0.4333,"name":"lunzhouyinfu/lunzhouyinfu_14"},{"time":0.4667,"name":"lunzhouyinfu/lunzhouyinfu_15"},{"time":0.5,"name":"lunzhouyinfu/lunzhouyinfu_16"},{"time":0.5333,"name":"lunzhouyinfu/lunzhouyinfu_17"},{"time":0.5667,"name":"lunzhouyinfu/lunzhouyinfu_18"},{"time":0.6,"name":"lunzhouyinfu/lunzhouyinfu_19"},{"time":0.6333,"name":"lunzhouyinfu/lunzhouyinfu_20"},{"time":0.6667,"name":"lunzhouyinfu/lunzhouyinfu_21"},{"time":0.7,"name":"lunzhouyinfu/lunzhouyinfu_22"},{"time":0.7333,"name":"lunzhouyinfu/lunzhouyinfu_23"},{"time":0.7667,"name":"lunzhouyinfu/lunzhouyinfu_24"},{"time":0.8,"name":"lunzhouyinfu/lunzhouyinfu_25"},{"time":0.8333,"name":"lunzhouyinfu/lunzhouyinfu_26"},{"time":0.8667,"name":"lunzhouyinfu/lunzhouyinfu_27"},{"time":0.9,"name":"lunzhouyinfu/lunzhouyinfu_28"},{"time":0.9333,"name":"lunzhouyinfu/lunzhouyinfu_29"},{"time":0.9667,"name":"lunzhouyinfu/lunzhouyinfu_30"},{"time":1,"name":"lunzhouyinfu/lunzhouyinfu_1"}]},"lunzhouyinfu/lunzhouyinfu_7":{"attachment":[{"time":0,"name":"lunzhouyinfu/lunzhouyinfu_1"},{"time":0.0333,"name":"lunzhouyinfu/lunzhouyinfu_2"},{"time":0.0667,"name":"lunzhouyinfu/lunzhouyinfu_3"},{"time":0.1,"name":"lunzhouyinfu/lunzhouyinfu_4"},{"time":0.1333,"name":"lunzhouyinfu/lunzhouyinfu_5"},{"time":0.1667,"name":"lunzhouyinfu/lunzhouyinfu_6"},{"time":0.2,"name":"lunzhouyinfu/lunzhouyinfu_7"},{"time":0.2333,"name":"lunzhouyinfu/lunzhouyinfu_8"},{"time":0.2667,"name":"lunzhouyinfu/lunzhouyinfu_9"},{"time":0.3,"name":"lunzhouyinfu/lunzhouyinfu_10"},{"time":0.3333,"name":"lunzhouyinfu/lunzhouyinfu_11"},{"time":0.3667,"name":"lunzhouyinfu/lunzhouyinfu_12"},{"time":0.4,"name":"lunzhouyinfu/lunzhouyinfu_13"},{"time":0.4333,"name":"lunzhouyinfu/lunzhouyinfu_14"},{"time":0.4667,"name":"lunzhouyinfu/lunzhouyinfu_15"},{"time":0.5,"name":"lunzhouyinfu/lunzhouyinfu_16"},{"time":0.5333,"name":"lunzhouyinfu/lunzhouyinfu_17"},{"time":0.5667,"name":"lunzhouyinfu/lunzhouyinfu_18"},{"time":0.6,"name":"lunzhouyinfu/lunzhouyinfu_19"},{"time":0.6333,"name":"lunzhouyinfu/lunzhouyinfu_20"},{"time":0.6667,"name":"lunzhouyinfu/lunzhouyinfu_21"},{"time":0.7,"name":"lunzhouyinfu/lunzhouyinfu_22"},{"time":0.7333,"name":"lunzhouyinfu/lunzhouyinfu_23"},{"time":0.7667,"name":"lunzhouyinfu/lunzhouyinfu_24"},{"time":0.8,"name":"lunzhouyinfu/lunzhouyinfu_25"},{"time":0.8333,"name":"lunzhouyinfu/lunzhouyinfu_26"},{"time":0.8667,"name":"lunzhouyinfu/lunzhouyinfu_27"},{"time":0.9,"name":"lunzhouyinfu/lunzhouyinfu_28"},{"time":0.9333,"name":"lunzhouyinfu/lunzhouyinfu_29"},{"time":0.9667,"name":"lunzhouyinfu/lunzhouyinfu_30"},{"time":1,"name":"lunzhouyinfu/lunzhouyinfu_1"}]},"lunzhouyinfu/lunzhouyinfu_8":{"attachment":[{"time":0,"name":"lunzhouyinfu/lunzhouyinfu_1"},{"time":0.0333,"name":"lunzhouyinfu/lunzhouyinfu_2"},{"time":0.0667,"name":"lunzhouyinfu/lunzhouyinfu_3"},{"time":0.1,"name":"lunzhouyinfu/lunzhouyinfu_4"},{"time":0.1333,"name":"lunzhouyinfu/lunzhouyinfu_5"},{"time":0.1667,"name":"lunzhouyinfu/lunzhouyinfu_6"},{"time":0.2,"name":"lunzhouyinfu/lunzhouyinfu_7"},{"time":0.2333,"name":"lunzhouyinfu/lunzhouyinfu_8"},{"time":0.2667,"name":"lunzhouyinfu/lunzhouyinfu_9"},{"time":0.3,"name":"lunzhouyinfu/lunzhouyinfu_10"},{"time":0.3333,"name":"lunzhouyinfu/lunzhouyinfu_11"},{"time":0.3667,"name":"lunzhouyinfu/lunzhouyinfu_12"},{"time":0.4,"name":"lunzhouyinfu/lunzhouyinfu_13"},{"time":0.4333,"name":"lunzhouyinfu/lunzhouyinfu_14"},{"time":0.4667,"name":"lunzhouyinfu/lunzhouyinfu_15"},{"time":0.5,"name":"lunzhouyinfu/lunzhouyinfu_16"},{"time":0.5333,"name":"lunzhouyinfu/lunzhouyinfu_17"},{"time":0.5667,"name":"lunzhouyinfu/lunzhouyinfu_18"},{"time":0.6,"name":"lunzhouyinfu/lunzhouyinfu_19"},{"time":0.6333,"name":"lunzhouyinfu/lunzhouyinfu_20"},{"time":0.6667,"name":"lunzhouyinfu/lunzhouyinfu_21"},{"time":0.7,"name":"lunzhouyinfu/lunzhouyinfu_22"},{"time":0.7333,"name":"lunzhouyinfu/lunzhouyinfu_23"},{"time":0.7667,"name":"lunzhouyinfu/lunzhouyinfu_24"},{"time":0.8,"name":"lunzhouyinfu/lunzhouyinfu_25"},{"time":0.8333,"name":"lunzhouyinfu/lunzhouyinfu_26"},{"time":0.8667,"name":"lunzhouyinfu/lunzhouyinfu_27"},{"time":0.9,"name":"lunzhouyinfu/lunzhouyinfu_28"},{"time":0.9333,"name":"lunzhouyinfu/lunzhouyinfu_29"},{"time":0.9667,"name":"lunzhouyinfu/lunzhouyinfu_30"},{"time":1,"name":"lunzhouyinfu/lunzhouyinfu_1"}]},"lunzhouyinfu/lunzhouyinfu_9":{"attachment":[{"time":0,"name":"lunzhouyinfu/lunzhouyinfu_1"},{"time":0.0333,"name":"lunzhouyinfu/lunzhouyinfu_2"},{"time":0.0667,"name":"lunzhouyinfu/lunzhouyinfu_3"},{"time":0.1,"name":"lunzhouyinfu/lunzhouyinfu_4"},{"time":0.1333,"name":"lunzhouyinfu/lunzhouyinfu_5"},{"time":0.1667,"name":"lunzhouyinfu/lunzhouyinfu_6"},{"time":0.2,"name":"lunzhouyinfu/lunzhouyinfu_7"},{"time":0.2333,"name":"lunzhouyinfu/lunzhouyinfu_8"},{"time":0.2667,"name":"lunzhouyinfu/lunzhouyinfu_9"},{"time":0.3,"name":"lunzhouyinfu/lunzhouyinfu_10"},{"time":0.3333,"name":"lunzhouyinfu/lunzhouyinfu_11"},{"time":0.3667,"name":"lunzhouyinfu/lunzhouyinfu_12"},{"time":0.4,"name":"lunzhouyinfu/lunzhouyinfu_13"},{"time":0.4333,"name":"lunzhouyinfu/lunzhouyinfu_14"},{"time":0.4667,"name":"lunzhouyinfu/lunzhouyinfu_15"},{"time":0.5,"name":"lunzhouyinfu/lunzhouyinfu_16"},{"time":0.5333,"name":"lunzhouyinfu/lunzhouyinfu_17"},{"time":0.5667,"name":"lunzhouyinfu/lunzhouyinfu_18"},{"time":0.6,"name":"lunzhouyinfu/lunzhouyinfu_19"},{"time":0.6333,"name":"lunzhouyinfu/lunzhouyinfu_20"},{"time":0.6667,"name":"lunzhouyinfu/lunzhouyinfu_21"},{"time":0.7,"name":"lunzhouyinfu/lunzhouyinfu_22"},{"time":0.7333,"name":"lunzhouyinfu/lunzhouyinfu_23"},{"time":0.7667,"name":"lunzhouyinfu/lunzhouyinfu_24"},{"time":0.8,"name":"lunzhouyinfu/lunzhouyinfu_25"},{"time":0.8333,"name":"lunzhouyinfu/lunzhouyinfu_26"},{"time":0.8667,"name":"lunzhouyinfu/lunzhouyinfu_27"},{"time":0.9,"name":"lunzhouyinfu/lunzhouyinfu_28"},{"time":0.9333,"name":"lunzhouyinfu/lunzhouyinfu_29"},{"time":0.9667,"name":"lunzhouyinfu/lunzhouyinfu_30"},{"time":1,"name":"lunzhouyinfu/lunzhouyinfu_1"}]},"lunzhouyinfu/lunzhouyinfu_10":{"attachment":[{"time":0,"name":"lunzhouyinfu/lunzhouyinfu_1"},{"time":0.0333,"name":"lunzhouyinfu/lunzhouyinfu_2"},{"time":0.0667,"name":"lunzhouyinfu/lunzhouyinfu_3"},{"time":0.1,"name":"lunzhouyinfu/lunzhouyinfu_4"},{"time":0.1333,"name":"lunzhouyinfu/lunzhouyinfu_5"},{"time":0.1667,"name":"lunzhouyinfu/lunzhouyinfu_6"},{"time":0.2,"name":"lunzhouyinfu/lunzhouyinfu_7"},{"time":0.2333,"name":"lunzhouyinfu/lunzhouyinfu_8"},{"time":0.2667,"name":"lunzhouyinfu/lunzhouyinfu_9"},{"time":0.3,"name":"lunzhouyinfu/lunzhouyinfu_10"},{"time":0.3333,"name":"lunzhouyinfu/lunzhouyinfu_11"},{"time":0.3667,"name":"lunzhouyinfu/lunzhouyinfu_12"},{"time":0.4,"name":"lunzhouyinfu/lunzhouyinfu_13"},{"time":0.4333,"name":"lunzhouyinfu/lunzhouyinfu_14"},{"time":0.4667,"name":"lunzhouyinfu/lunzhouyinfu_15"},{"time":0.5,"name":"lunzhouyinfu/lunzhouyinfu_16"},{"time":0.5333,"name":"lunzhouyinfu/lunzhouyinfu_17"},{"time":0.5667,"name":"lunzhouyinfu/lunzhouyinfu_18"},{"time":0.6,"name":"lunzhouyinfu/lunzhouyinfu_19"},{"time":0.6333,"name":"lunzhouyinfu/lunzhouyinfu_20"},{"time":0.6667,"name":"lunzhouyinfu/lunzhouyinfu_21"},{"time":0.7,"name":"lunzhouyinfu/lunzhouyinfu_22"},{"time":0.7333,"name":"lunzhouyinfu/lunzhouyinfu_23"},{"time":0.7667,"name":"lunzhouyinfu/lunzhouyinfu_24"},{"time":0.8,"name":"lunzhouyinfu/lunzhouyinfu_25"},{"time":0.8333,"name":"lunzhouyinfu/lunzhouyinfu_26"},{"time":0.8667,"name":"lunzhouyinfu/lunzhouyinfu_27"},{"time":0.9,"name":"lunzhouyinfu/lunzhouyinfu_28"},{"time":0.9333,"name":"lunzhouyinfu/lunzhouyinfu_29"},{"time":0.9667,"name":"lunzhouyinfu/lunzhouyinfu_30"},{"time":1,"name":"lunzhouyinfu/lunzhouyinfu_1"}]},"menghei":{"color":[{"time":0,"color":"ffffff73"}]},"menghei/menghei_1":{"attachment":[{"time":0,"name":null}]}}},"animation3":{"slots":{"lunzhouyinfu/lunzhouyinfu_1":{"color":[{"time":0,"color":"ffffffff","curve":[0.25,0,0.75,1]},{"time":0.3333,"color":"ffffff00"}],"attachment":[{"time":0,"name":"lunzhouyinfu/lunzhouyinfu_1"},{"time":0.0333,"name":"lunzhouyinfu/lunzhouyinfu_2"},{"time":0.0667,"name":"lunzhouyinfu/lunzhouyinfu_3"},{"time":0.1,"name":"lunzhouyinfu/lunzhouyinfu_4"},{"time":0.1333,"name":"lunzhouyinfu/lunzhouyinfu_5"},{"time":0.1667,"name":"lunzhouyinfu/lunzhouyinfu_6"},{"time":0.2,"name":"lunzhouyinfu/lunzhouyinfu_7"},{"time":0.2333,"name":"lunzhouyinfu/lunzhouyinfu_8"},{"time":0.2667,"name":"lunzhouyinfu/lunzhouyinfu_9"},{"time":0.3,"name":"lunzhouyinfu/lunzhouyinfu_10"},{"time":0.3333,"name":"lunzhouyinfu/lunzhouyinfu_11"},{"time":0.3667,"name":"lunzhouyinfu/lunzhouyinfu_12"},{"time":0.4,"name":"lunzhouyinfu/lunzhouyinfu_13"},{"time":0.4333,"name":"lunzhouyinfu/lunzhouyinfu_14"},{"time":0.4667,"name":"lunzhouyinfu/lunzhouyinfu_15"},{"time":0.5,"name":"lunzhouyinfu/lunzhouyinfu_16"},{"time":0.5333,"name":"lunzhouyinfu/lunzhouyinfu_17"},{"time":0.5667,"name":"lunzhouyinfu/lunzhouyinfu_18"},{"time":0.6,"name":"lunzhouyinfu/lunzhouyinfu_19"},{"time":0.6333,"name":"lunzhouyinfu/lunzhouyinfu_20"},{"time":0.6667,"name":"lunzhouyinfu/lunzhouyinfu_21"},{"time":0.7,"name":"lunzhouyinfu/lunzhouyinfu_22"},{"time":0.7333,"name":"lunzhouyinfu/lunzhouyinfu_23"},{"time":0.7667,"name":"lunzhouyinfu/lunzhouyinfu_24"},{"time":0.8,"name":"lunzhouyinfu/lunzhouyinfu_25"},{"time":0.8333,"name":"lunzhouyinfu/lunzhouyinfu_26"},{"time":0.8667,"name":"lunzhouyinfu/lunzhouyinfu_27"},{"time":0.9,"name":"lunzhouyinfu/lunzhouyinfu_28"},{"time":0.9333,"name":"lunzhouyinfu/lunzhouyinfu_29"},{"time":0.9667,"name":"lunzhouyinfu/lunzhouyinfu_30"},{"time":1,"name":"lunzhouyinfu/lunzhouyinfu_1"}]},"lunzhouyinfu/lunzhouyinfu_2":{"color":[{"time":0,"color":"ffffffff","curve":[0.25,0,0.75,1]},{"time":0.3333,"color":"ffffff00"}],"attachment":[{"time":0,"name":"lunzhouyinfu/lunzhouyinfu_1"},{"time":0.0333,"name":"lunzhouyinfu/lunzhouyinfu_2"},{"time":0.0667,"name":"lunzhouyinfu/lunzhouyinfu_3"},{"time":0.1,"name":"lunzhouyinfu/lunzhouyinfu_4"},{"time":0.1333,"name":"lunzhouyinfu/lunzhouyinfu_5"},{"time":0.1667,"name":"lunzhouyinfu/lunzhouyinfu_6"},{"time":0.2,"name":"lunzhouyinfu/lunzhouyinfu_7"},{"time":0.2333,"name":"lunzhouyinfu/lunzhouyinfu_8"},{"time":0.2667,"name":"lunzhouyinfu/lunzhouyinfu_9"},{"time":0.3,"name":"lunzhouyinfu/lunzhouyinfu_10"},{"time":0.3333,"name":"lunzhouyinfu/lunzhouyinfu_11"},{"time":0.3667,"name":"lunzhouyinfu/lunzhouyinfu_12"},{"time":0.4,"name":"lunzhouyinfu/lunzhouyinfu_13"},{"time":0.4333,"name":"lunzhouyinfu/lunzhouyinfu_14"},{"time":0.4667,"name":"lunzhouyinfu/lunzhouyinfu_15"},{"time":0.5,"name":"lunzhouyinfu/lunzhouyinfu_16"},{"time":0.5333,"name":"lunzhouyinfu/lunzhouyinfu_17"},{"time":0.5667,"name":"lunzhouyinfu/lunzhouyinfu_18"},{"time":0.6,"name":"lunzhouyinfu/lunzhouyinfu_19"},{"time":0.6333,"name":"lunzhouyinfu/lunzhouyinfu_20"},{"time":0.6667,"name":"lunzhouyinfu/lunzhouyinfu_21"},{"time":0.7,"name":"lunzhouyinfu/lunzhouyinfu_22"},{"time":0.7333,"name":"lunzhouyinfu/lunzhouyinfu_23"},{"time":0.7667,"name":"lunzhouyinfu/lunzhouyinfu_24"},{"time":0.8,"name":"lunzhouyinfu/lunzhouyinfu_25"},{"time":0.8333,"name":"lunzhouyinfu/lunzhouyinfu_26"},{"time":0.8667,"name":"lunzhouyinfu/lunzhouyinfu_27"},{"time":0.9,"name":"lunzhouyinfu/lunzhouyinfu_28"},{"time":0.9333,"name":"lunzhouyinfu/lunzhouyinfu_29"},{"time":0.9667,"name":"lunzhouyinfu/lunzhouyinfu_30"},{"time":1,"name":"lunzhouyinfu/lunzhouyinfu_1"}]},"lunzhouyinfu/lunzhouyinfu_3":{"color":[{"time":0,"color":"ffffffff","curve":[0.25,0,0.75,1]},{"time":0.3333,"color":"ffffff00"}],"attachment":[{"time":0,"name":"lunzhouyinfu/lunzhouyinfu_1"},{"time":0.0333,"name":"lunzhouyinfu/lunzhouyinfu_2"},{"time":0.0667,"name":"lunzhouyinfu/lunzhouyinfu_3"},{"time":0.1,"name":"lunzhouyinfu/lunzhouyinfu_4"},{"time":0.1333,"name":"lunzhouyinfu/lunzhouyinfu_5"},{"time":0.1667,"name":"lunzhouyinfu/lunzhouyinfu_6"},{"time":0.2,"name":"lunzhouyinfu/lunzhouyinfu_7"},{"time":0.2333,"name":"lunzhouyinfu/lunzhouyinfu_8"},{"time":0.2667,"name":"lunzhouyinfu/lunzhouyinfu_9"},{"time":0.3,"name":"lunzhouyinfu/lunzhouyinfu_10"},{"time":0.3333,"name":"lunzhouyinfu/lunzhouyinfu_11"},{"time":0.3667,"name":"lunzhouyinfu/lunzhouyinfu_12"},{"time":0.4,"name":"lunzhouyinfu/lunzhouyinfu_13"},{"time":0.4333,"name":"lunzhouyinfu/lunzhouyinfu_14"},{"time":0.4667,"name":"lunzhouyinfu/lunzhouyinfu_15"},{"time":0.5,"name":"lunzhouyinfu/lunzhouyinfu_16"},{"time":0.5333,"name":"lunzhouyinfu/lunzhouyinfu_17"},{"time":0.5667,"name":"lunzhouyinfu/lunzhouyinfu_18"},{"time":0.6,"name":"lunzhouyinfu/lunzhouyinfu_19"},{"time":0.6333,"name":"lunzhouyinfu/lunzhouyinfu_20"},{"time":0.6667,"name":"lunzhouyinfu/lunzhouyinfu_21"},{"time":0.7,"name":"lunzhouyinfu/lunzhouyinfu_22"},{"time":0.7333,"name":"lunzhouyinfu/lunzhouyinfu_23"},{"time":0.7667,"name":"lunzhouyinfu/lunzhouyinfu_24"},{"time":0.8,"name":"lunzhouyinfu/lunzhouyinfu_25"},{"time":0.8333,"name":"lunzhouyinfu/lunzhouyinfu_26"},{"time":0.8667,"name":"lunzhouyinfu/lunzhouyinfu_27"},{"time":0.9,"name":"lunzhouyinfu/lunzhouyinfu_28"},{"time":0.9333,"name":"lunzhouyinfu/lunzhouyinfu_29"},{"time":0.9667,"name":"lunzhouyinfu/lunzhouyinfu_30"},{"time":1,"name":"lunzhouyinfu/lunzhouyinfu_1"}]},"lunzhouyinfu/lunzhouyinfu_4":{"color":[{"time":0,"color":"ffffffff","curve":[0.25,0,0.75,1]},{"time":0.3333,"color":"ffffff00"}],"attachment":[{"time":0,"name":"lunzhouyinfu/lunzhouyinfu_1"},{"time":0.0333,"name":"lunzhouyinfu/lunzhouyinfu_2"},{"time":0.0667,"name":"lunzhouyinfu/lunzhouyinfu_3"},{"time":0.1,"name":"lunzhouyinfu/lunzhouyinfu_4"},{"time":0.1333,"name":"lunzhouyinfu/lunzhouyinfu_5"},{"time":0.1667,"name":"lunzhouyinfu/lunzhouyinfu_6"},{"time":0.2,"name":"lunzhouyinfu/lunzhouyinfu_7"},{"time":0.2333,"name":"lunzhouyinfu/lunzhouyinfu_8"},{"time":0.2667,"name":"lunzhouyinfu/lunzhouyinfu_9"},{"time":0.3,"name":"lunzhouyinfu/lunzhouyinfu_10"},{"time":0.3333,"name":"lunzhouyinfu/lunzhouyinfu_11"},{"time":0.3667,"name":"lunzhouyinfu/lunzhouyinfu_12"},{"time":0.4,"name":"lunzhouyinfu/lunzhouyinfu_13"},{"time":0.4333,"name":"lunzhouyinfu/lunzhouyinfu_14"},{"time":0.4667,"name":"lunzhouyinfu/lunzhouyinfu_15"},{"time":0.5,"name":"lunzhouyinfu/lunzhouyinfu_16"},{"time":0.5333,"name":"lunzhouyinfu/lunzhouyinfu_17"},{"time":0.5667,"name":"lunzhouyinfu/lunzhouyinfu_18"},{"time":0.6,"name":"lunzhouyinfu/lunzhouyinfu_19"},{"time":0.6333,"name":"lunzhouyinfu/lunzhouyinfu_20"},{"time":0.6667,"name":"lunzhouyinfu/lunzhouyinfu_21"},{"time":0.7,"name":"lunzhouyinfu/lunzhouyinfu_22"},{"time":0.7333,"name":"lunzhouyinfu/lunzhouyinfu_23"},{"time":0.7667,"name":"lunzhouyinfu/lunzhouyinfu_24"},{"time":0.8,"name":"lunzhouyinfu/lunzhouyinfu_25"},{"time":0.8333,"name":"lunzhouyinfu/lunzhouyinfu_26"},{"time":0.8667,"name":"lunzhouyinfu/lunzhouyinfu_27"},{"time":0.9,"name":"lunzhouyinfu/lunzhouyinfu_28"},{"time":0.9333,"name":"lunzhouyinfu/lunzhouyinfu_29"},{"time":0.9667,"name":"lunzhouyinfu/lunzhouyinfu_30"},{"time":1,"name":"lunzhouyinfu/lunzhouyinfu_1"}]},"lunzhouyinfu/lunzhouyinfu_5":{"color":[{"time":0,"color":"ffffffff","curve":[0.25,0,0.75,1]},{"time":0.3333,"color":"ffffff00"}],"attachment":[{"time":0,"name":"lunzhouyinfu/lunzhouyinfu_1"},{"time":0.0333,"name":"lunzhouyinfu/lunzhouyinfu_2"},{"time":0.0667,"name":"lunzhouyinfu/lunzhouyinfu_3"},{"time":0.1,"name":"lunzhouyinfu/lunzhouyinfu_4"},{"time":0.1333,"name":"lunzhouyinfu/lunzhouyinfu_5"},{"time":0.1667,"name":"lunzhouyinfu/lunzhouyinfu_6"},{"time":0.2,"name":"lunzhouyinfu/lunzhouyinfu_7"},{"time":0.2333,"name":"lunzhouyinfu/lunzhouyinfu_8"},{"time":0.2667,"name":"lunzhouyinfu/lunzhouyinfu_9"},{"time":0.3,"name":"lunzhouyinfu/lunzhouyinfu_10"},{"time":0.3333,"name":"lunzhouyinfu/lunzhouyinfu_11"},{"time":0.3667,"name":"lunzhouyinfu/lunzhouyinfu_12"},{"time":0.4,"name":"lunzhouyinfu/lunzhouyinfu_13"},{"time":0.4333,"name":"lunzhouyinfu/lunzhouyinfu_14"},{"time":0.4667,"name":"lunzhouyinfu/lunzhouyinfu_15"},{"time":0.5,"name":"lunzhouyinfu/lunzhouyinfu_16"},{"time":0.5333,"name":"lunzhouyinfu/lunzhouyinfu_17"},{"time":0.5667,"name":"lunzhouyinfu/lunzhouyinfu_18"},{"time":0.6,"name":"lunzhouyinfu/lunzhouyinfu_19"},{"time":0.6333,"name":"lunzhouyinfu/lunzhouyinfu_20"},{"time":0.6667,"name":"lunzhouyinfu/lunzhouyinfu_21"},{"time":0.7,"name":"lunzhouyinfu/lunzhouyinfu_22"},{"time":0.7333,"name":"lunzhouyinfu/lunzhouyinfu_23"},{"time":0.7667,"name":"lunzhouyinfu/lunzhouyinfu_24"},{"time":0.8,"name":"lunzhouyinfu/lunzhouyinfu_25"},{"time":0.8333,"name":"lunzhouyinfu/lunzhouyinfu_26"},{"time":0.8667,"name":"lunzhouyinfu/lunzhouyinfu_27"},{"time":0.9,"name":"lunzhouyinfu/lunzhouyinfu_28"},{"time":0.9333,"name":"lunzhouyinfu/lunzhouyinfu_29"},{"time":0.9667,"name":"lunzhouyinfu/lunzhouyinfu_30"},{"time":1,"name":"lunzhouyinfu/lunzhouyinfu_1"}]},"lunzhouyinfu/lunzhouyinfu_6":{"color":[{"time":0,"color":"ffffffff","curve":[0.25,0,0.75,1]},{"time":0.3333,"color":"ffffff00"}],"attachment":[{"time":0,"name":"lunzhouyinfu/lunzhouyinfu_1"},{"time":0.0333,"name":"lunzhouyinfu/lunzhouyinfu_2"},{"time":0.0667,"name":"lunzhouyinfu/lunzhouyinfu_3"},{"time":0.1,"name":"lunzhouyinfu/lunzhouyinfu_4"},{"time":0.1333,"name":"lunzhouyinfu/lunzhouyinfu_5"},{"time":0.1667,"name":"lunzhouyinfu/lunzhouyinfu_6"},{"time":0.2,"name":"lunzhouyinfu/lunzhouyinfu_7"},{"time":0.2333,"name":"lunzhouyinfu/lunzhouyinfu_8"},{"time":0.2667,"name":"lunzhouyinfu/lunzhouyinfu_9"},{"time":0.3,"name":"lunzhouyinfu/lunzhouyinfu_10"},{"time":0.3333,"name":"lunzhouyinfu/lunzhouyinfu_11"},{"time":0.3667,"name":"lunzhouyinfu/lunzhouyinfu_12"},{"time":0.4,"name":"lunzhouyinfu/lunzhouyinfu_13"},{"time":0.4333,"name":"lunzhouyinfu/lunzhouyinfu_14"},{"time":0.4667,"name":"lunzhouyinfu/lunzhouyinfu_15"},{"time":0.5,"name":"lunzhouyinfu/lunzhouyinfu_16"},{"time":0.5333,"name":"lunzhouyinfu/lunzhouyinfu_17"},{"time":0.5667,"name":"lunzhouyinfu/lunzhouyinfu_18"},{"time":0.6,"name":"lunzhouyinfu/lunzhouyinfu_19"},{"time":0.6333,"name":"lunzhouyinfu/lunzhouyinfu_20"},{"time":0.6667,"name":"lunzhouyinfu/lunzhouyinfu_21"},{"time":0.7,"name":"lunzhouyinfu/lunzhouyinfu_22"},{"time":0.7333,"name":"lunzhouyinfu/lunzhouyinfu_23"},{"time":0.7667,"name":"lunzhouyinfu/lunzhouyinfu_24"},{"time":0.8,"name":"lunzhouyinfu/lunzhouyinfu_25"},{"time":0.8333,"name":"lunzhouyinfu/lunzhouyinfu_26"},{"time":0.8667,"name":"lunzhouyinfu/lunzhouyinfu_27"},{"time":0.9,"name":"lunzhouyinfu/lunzhouyinfu_28"},{"time":0.9333,"name":"lunzhouyinfu/lunzhouyinfu_29"},{"time":0.9667,"name":"lunzhouyinfu/lunzhouyinfu_30"},{"time":1,"name":"lunzhouyinfu/lunzhouyinfu_1"}]},"lunzhouyinfu/lunzhouyinfu_7":{"color":[{"time":0,"color":"ffffffff","curve":[0.25,0,0.75,1]},{"time":0.3333,"color":"ffffff00"}],"attachment":[{"time":0,"name":"lunzhouyinfu/lunzhouyinfu_1"},{"time":0.0333,"name":"lunzhouyinfu/lunzhouyinfu_2"},{"time":0.0667,"name":"lunzhouyinfu/lunzhouyinfu_3"},{"time":0.1,"name":"lunzhouyinfu/lunzhouyinfu_4"},{"time":0.1333,"name":"lunzhouyinfu/lunzhouyinfu_5"},{"time":0.1667,"name":"lunzhouyinfu/lunzhouyinfu_6"},{"time":0.2,"name":"lunzhouyinfu/lunzhouyinfu_7"},{"time":0.2333,"name":"lunzhouyinfu/lunzhouyinfu_8"},{"time":0.2667,"name":"lunzhouyinfu/lunzhouyinfu_9"},{"time":0.3,"name":"lunzhouyinfu/lunzhouyinfu_10"},{"time":0.3333,"name":"lunzhouyinfu/lunzhouyinfu_11"},{"time":0.3667,"name":"lunzhouyinfu/lunzhouyinfu_12"},{"time":0.4,"name":"lunzhouyinfu/lunzhouyinfu_13"},{"time":0.4333,"name":"lunzhouyinfu/lunzhouyinfu_14"},{"time":0.4667,"name":"lunzhouyinfu/lunzhouyinfu_15"},{"time":0.5,"name":"lunzhouyinfu/lunzhouyinfu_16"},{"time":0.5333,"name":"lunzhouyinfu/lunzhouyinfu_17"},{"time":0.5667,"name":"lunzhouyinfu/lunzhouyinfu_18"},{"time":0.6,"name":"lunzhouyinfu/lunzhouyinfu_19"},{"time":0.6333,"name":"lunzhouyinfu/lunzhouyinfu_20"},{"time":0.6667,"name":"lunzhouyinfu/lunzhouyinfu_21"},{"time":0.7,"name":"lunzhouyinfu/lunzhouyinfu_22"},{"time":0.7333,"name":"lunzhouyinfu/lunzhouyinfu_23"},{"time":0.7667,"name":"lunzhouyinfu/lunzhouyinfu_24"},{"time":0.8,"name":"lunzhouyinfu/lunzhouyinfu_25"},{"time":0.8333,"name":"lunzhouyinfu/lunzhouyinfu_26"},{"time":0.8667,"name":"lunzhouyinfu/lunzhouyinfu_27"},{"time":0.9,"name":"lunzhouyinfu/lunzhouyinfu_28"},{"time":0.9333,"name":"lunzhouyinfu/lunzhouyinfu_29"},{"time":0.9667,"name":"lunzhouyinfu/lunzhouyinfu_30"},{"time":1,"name":"lunzhouyinfu/lunzhouyinfu_1"}]},"lunzhouyinfu/lunzhouyinfu_8":{"color":[{"time":0,"color":"ffffffff","curve":[0.25,0,0.75,1]},{"time":0.3333,"color":"ffffff00"}],"attachment":[{"time":0,"name":"lunzhouyinfu/lunzhouyinfu_1"},{"time":0.0333,"name":"lunzhouyinfu/lunzhouyinfu_2"},{"time":0.0667,"name":"lunzhouyinfu/lunzhouyinfu_3"},{"time":0.1,"name":"lunzhouyinfu/lunzhouyinfu_4"},{"time":0.1333,"name":"lunzhouyinfu/lunzhouyinfu_5"},{"time":0.1667,"name":"lunzhouyinfu/lunzhouyinfu_6"},{"time":0.2,"name":"lunzhouyinfu/lunzhouyinfu_7"},{"time":0.2333,"name":"lunzhouyinfu/lunzhouyinfu_8"},{"time":0.2667,"name":"lunzhouyinfu/lunzhouyinfu_9"},{"time":0.3,"name":"lunzhouyinfu/lunzhouyinfu_10"},{"time":0.3333,"name":"lunzhouyinfu/lunzhouyinfu_11"},{"time":0.3667,"name":"lunzhouyinfu/lunzhouyinfu_12"},{"time":0.4,"name":"lunzhouyinfu/lunzhouyinfu_13"},{"time":0.4333,"name":"lunzhouyinfu/lunzhouyinfu_14"},{"time":0.4667,"name":"lunzhouyinfu/lunzhouyinfu_15"},{"time":0.5,"name":"lunzhouyinfu/lunzhouyinfu_16"},{"time":0.5333,"name":"lunzhouyinfu/lunzhouyinfu_17"},{"time":0.5667,"name":"lunzhouyinfu/lunzhouyinfu_18"},{"time":0.6,"name":"lunzhouyinfu/lunzhouyinfu_19"},{"time":0.6333,"name":"lunzhouyinfu/lunzhouyinfu_20"},{"time":0.6667,"name":"lunzhouyinfu/lunzhouyinfu_21"},{"time":0.7,"name":"lunzhouyinfu/lunzhouyinfu_22"},{"time":0.7333,"name":"lunzhouyinfu/lunzhouyinfu_23"},{"time":0.7667,"name":"lunzhouyinfu/lunzhouyinfu_24"},{"time":0.8,"name":"lunzhouyinfu/lunzhouyinfu_25"},{"time":0.8333,"name":"lunzhouyinfu/lunzhouyinfu_26"},{"time":0.8667,"name":"lunzhouyinfu/lunzhouyinfu_27"},{"time":0.9,"name":"lunzhouyinfu/lunzhouyinfu_28"},{"time":0.9333,"name":"lunzhouyinfu/lunzhouyinfu_29"},{"time":0.9667,"name":"lunzhouyinfu/lunzhouyinfu_30"},{"time":1,"name":"lunzhouyinfu/lunzhouyinfu_1"}]},"lunzhouyinfu/lunzhouyinfu_9":{"color":[{"time":0,"color":"ffffffff","curve":[0.25,0,0.75,1]},{"time":0.3333,"color":"ffffff00"}],"attachment":[{"time":0,"name":"lunzhouyinfu/lunzhouyinfu_1"},{"time":0.0333,"name":"lunzhouyinfu/lunzhouyinfu_2"},{"time":0.0667,"name":"lunzhouyinfu/lunzhouyinfu_3"},{"time":0.1,"name":"lunzhouyinfu/lunzhouyinfu_4"},{"time":0.1333,"name":"lunzhouyinfu/lunzhouyinfu_5"},{"time":0.1667,"name":"lunzhouyinfu/lunzhouyinfu_6"},{"time":0.2,"name":"lunzhouyinfu/lunzhouyinfu_7"},{"time":0.2333,"name":"lunzhouyinfu/lunzhouyinfu_8"},{"time":0.2667,"name":"lunzhouyinfu/lunzhouyinfu_9"},{"time":0.3,"name":"lunzhouyinfu/lunzhouyinfu_10"},{"time":0.3333,"name":"lunzhouyinfu/lunzhouyinfu_11"},{"time":0.3667,"name":"lunzhouyinfu/lunzhouyinfu_12"},{"time":0.4,"name":"lunzhouyinfu/lunzhouyinfu_13"},{"time":0.4333,"name":"lunzhouyinfu/lunzhouyinfu_14"},{"time":0.4667,"name":"lunzhouyinfu/lunzhouyinfu_15"},{"time":0.5,"name":"lunzhouyinfu/lunzhouyinfu_16"},{"time":0.5333,"name":"lunzhouyinfu/lunzhouyinfu_17"},{"time":0.5667,"name":"lunzhouyinfu/lunzhouyinfu_18"},{"time":0.6,"name":"lunzhouyinfu/lunzhouyinfu_19"},{"time":0.6333,"name":"lunzhouyinfu/lunzhouyinfu_20"},{"time":0.6667,"name":"lunzhouyinfu/lunzhouyinfu_21"},{"time":0.7,"name":"lunzhouyinfu/lunzhouyinfu_22"},{"time":0.7333,"name":"lunzhouyinfu/lunzhouyinfu_23"},{"time":0.7667,"name":"lunzhouyinfu/lunzhouyinfu_24"},{"time":0.8,"name":"lunzhouyinfu/lunzhouyinfu_25"},{"time":0.8333,"name":"lunzhouyinfu/lunzhouyinfu_26"},{"time":0.8667,"name":"lunzhouyinfu/lunzhouyinfu_27"},{"time":0.9,"name":"lunzhouyinfu/lunzhouyinfu_28"},{"time":0.9333,"name":"lunzhouyinfu/lunzhouyinfu_29"},{"time":0.9667,"name":"lunzhouyinfu/lunzhouyinfu_30"},{"time":1,"name":"lunzhouyinfu/lunzhouyinfu_1"}]},"lunzhouyinfu/lunzhouyinfu_10":{"color":[{"time":0,"color":"ffffffff","curve":[0.25,0,0.75,1]},{"time":0.3333,"color":"ffffff00"}],"attachment":[{"time":0,"name":"lunzhouyinfu/lunzhouyinfu_1"},{"time":0.0333,"name":"lunzhouyinfu/lunzhouyinfu_2"},{"time":0.0667,"name":"lunzhouyinfu/lunzhouyinfu_3"},{"time":0.1,"name":"lunzhouyinfu/lunzhouyinfu_4"},{"time":0.1333,"name":"lunzhouyinfu/lunzhouyinfu_5"},{"time":0.1667,"name":"lunzhouyinfu/lunzhouyinfu_6"},{"time":0.2,"name":"lunzhouyinfu/lunzhouyinfu_7"},{"time":0.2333,"name":"lunzhouyinfu/lunzhouyinfu_8"},{"time":0.2667,"name":"lunzhouyinfu/lunzhouyinfu_9"},{"time":0.3,"name":"lunzhouyinfu/lunzhouyinfu_10"},{"time":0.3333,"name":"lunzhouyinfu/lunzhouyinfu_11"},{"time":0.3667,"name":"lunzhouyinfu/lunzhouyinfu_12"},{"time":0.4,"name":"lunzhouyinfu/lunzhouyinfu_13"},{"time":0.4333,"name":"lunzhouyinfu/lunzhouyinfu_14"},{"time":0.4667,"name":"lunzhouyinfu/lunzhouyinfu_15"},{"time":0.5,"name":"lunzhouyinfu/lunzhouyinfu_16"},{"time":0.5333,"name":"lunzhouyinfu/lunzhouyinfu_17"},{"time":0.5667,"name":"lunzhouyinfu/lunzhouyinfu_18"},{"time":0.6,"name":"lunzhouyinfu/lunzhouyinfu_19"},{"time":0.6333,"name":"lunzhouyinfu/lunzhouyinfu_20"},{"time":0.6667,"name":"lunzhouyinfu/lunzhouyinfu_21"},{"time":0.7,"name":"lunzhouyinfu/lunzhouyinfu_22"},{"time":0.7333,"name":"lunzhouyinfu/lunzhouyinfu_23"},{"time":0.7667,"name":"lunzhouyinfu/lunzhouyinfu_24"},{"time":0.8,"name":"lunzhouyinfu/lunzhouyinfu_25"},{"time":0.8333,"name":"lunzhouyinfu/lunzhouyinfu_26"},{"time":0.8667,"name":"lunzhouyinfu/lunzhouyinfu_27"},{"time":0.9,"name":"lunzhouyinfu/lunzhouyinfu_28"},{"time":0.9333,"name":"lunzhouyinfu/lunzhouyinfu_29"},{"time":0.9667,"name":"lunzhouyinfu/lunzhouyinfu_30"},{"time":1,"name":"lunzhouyinfu/lunzhouyinfu_1"}]},"menghei":{"color":[{"time":0,"color":"ffffff73"}],"attachment":[{"time":0,"name":"menghei"},{"time":0.0333,"name":null}]},"menghei/menghei_1":{"attachment":[{"time":0,"name":null},{"time":0.0333,"name":"menghei/menghei_1"},{"time":0.0667,"name":"menghei/menghei_2"},{"time":0.1,"name":"menghei/menghei_3"},{"time":0.1333,"name":"menghei/menghei_4"},{"time":0.1667,"name":"menghei/menghei_5"},{"time":0.2,"name":"menghei/menghei_6"},{"time":0.2333,"name":"menghei/menghei_7"},{"time":0.2667,"name":"menghei/menghei_8"},{"time":0.3,"name":"menghei/menghei_9"},{"time":0.3333,"name":"menghei/menghei_10"},{"time":0.3667,"name":"menghei/menghei_11"},{"time":0.4,"name":"menghei/menghei_12"},{"time":0.4333,"name":"menghei/menghei_13"},{"time":0.4667,"name":"menghei/menghei_14"},{"time":0.5,"name":"menghei/menghei_15"},{"time":0.5333,"name":"menghei/menghei_16"},{"time":0.5667,"name":"menghei/menghei_17"},{"time":0.6,"name":"menghei/menghei_18"},{"time":0.6333,"name":"menghei/menghei_19"},{"time":0.6667,"name":"menghei/menghei_20"},{"time":0.7,"name":"menghei/menghei_21"},{"time":0.7333,"name":"menghei/menghei_22"},{"time":0.7667,"name":"menghei/menghei_23"},{"time":0.8,"name":"menghei/menghei_24"},{"time":0.8333,"name":"menghei/menghei_25"},{"time":0.8667,"name":"menghei/menghei_26"},{"time":0.9,"name":"menghei/menghei_27"},{"time":0.9333,"name":"menghei/menghei_28"},{"time":0.9667,"name":"menghei/menghei_29"},{"time":1,"name":"menghei/menghei_30"},{"time":1.0333,"name":"menghei/menghei_31"},{"time":1.0667,"name":"menghei/menghei_32"},{"time":1.1,"name":"menghei/menghei_33"},{"time":1.1333,"name":"menghei/menghei_34"},{"time":1.1667,"name":"menghei/menghei_35"},{"time":1.2,"name":"menghei/menghei_36"},{"time":1.2333,"name":"menghei/menghei_37"},{"time":1.2667,"name":"menghei/menghei_38"},{"time":1.3,"name":"menghei/menghei_39"},{"time":1.3333,"name":null}]}}}}},"_atlasText":"\nlunzhou_01.png\nsize: 1924,1167\nformat: RGBA8888\nfilter: Linear,Linear\nrepeat: none\nlunzhouyinfu/lunzhouyinfu_1\n  rotate: false\n  xy: 1348, 5\n  size: 55, 246\n  orig: 71, 254\n  offset: 5, 4\n  index: -1\nlunzhouyinfu/lunzhouyinfu_10\n  rotate: false\n  xy: 1414, 621\n  size: 67, 236\n  orig: 71, 254\n  offset: 2, 6\n  index: -1\nlunzhouyinfu/lunzhouyinfu_11\n  rotate: false\n  xy: 1413, 382\n  size: 66, 237\n  orig: 71, 254\n  offset: 3, 6\n  index: -1\nlunzhouyinfu/lunzhouyinfu_12\n  rotate: false\n  xy: 1481, 374\n  size: 66, 238\n  orig: 71, 254\n  offset: 3, 6\n  index: -1\nlunzhouyinfu/lunzhouyinfu_13\n  rotate: false\n  xy: 1615, 369\n  size: 63, 239\n  orig: 71, 254\n  offset: 5, 5\n  index: -1\nlunzhouyinfu/lunzhouyinfu_14\n  rotate: false\n  xy: 1775, 172\n  size: 58, 241\n  orig: 71, 254\n  offset: 6, 4\n  index: -1\nlunzhouyinfu/lunzhouyinfu_15\n  rotate: false\n  xy: 1595, 126\n  size: 59, 241\n  orig: 71, 254\n  offset: 5, 4\n  index: -1\nlunzhouyinfu/lunzhouyinfu_16\n  rotate: false\n  xy: 1532, 126\n  size: 61, 243\n  orig: 71, 254\n  offset: 4, 3\n  index: -1\nlunzhouyinfu/lunzhouyinfu_17\n  rotate: false\n  xy: 1811, 923\n  size: 62, 244\n  orig: 71, 254\n  offset: 4, 2\n  index: -1\nlunzhouyinfu/lunzhouyinfu_18\n  rotate: false\n  xy: 1552, 613\n  size: 64, 244\n  orig: 71, 254\n  offset: 4, 2\n  index: -1\nlunzhouyinfu/lunzhouyinfu_19\n  rotate: false\n  xy: 1280, 7\n  size: 66, 244\n  orig: 71, 254\n  offset: 3, 2\n  index: -1\nlunzhouyinfu/lunzhouyinfu_2\n  rotate: false\n  xy: 1618, 610\n  size: 56, 247\n  orig: 71, 254\n  offset: 6, 4\n  index: -1\nlunzhouyinfu/lunzhouyinfu_20\n  rotate: false\n  xy: 1211, 7\n  size: 67, 244\n  orig: 71, 254\n  offset: 4, 2\n  index: -1\nlunzhouyinfu/lunzhouyinfu_21\n  rotate: false\n  xy: 1483, 614\n  size: 67, 243\n  orig: 71, 254\n  offset: 4, 4\n  index: -1\nlunzhouyinfu/lunzhouyinfu_22\n  rotate: false\n  xy: 1008, 0\n  size: 68, 243\n  orig: 71, 254\n  offset: 3, 4\n  index: -1\nlunzhouyinfu/lunzhouyinfu_23\n  rotate: false\n  xy: 1141, 5\n  size: 68, 246\n  orig: 71, 254\n  offset: 3, 3\n  index: -1\nlunzhouyinfu/lunzhouyinfu_24\n  rotate: false\n  xy: 1468, 126\n  size: 62, 246\n  orig: 71, 254\n  offset: 2, 3\n  index: -1\nlunzhouyinfu/lunzhouyinfu_25\n  rotate: false\n  xy: 1805, 422\n  size: 62, 248\n  orig: 71, 254\n  offset: 3, 3\n  index: -1\nlunzhouyinfu/lunzhouyinfu_26\n  rotate: false\n  xy: 1405, 132\n  size: 61, 248\n  orig: 71, 254\n  offset: 3, 3\n  index: -1\nlunzhouyinfu/lunzhouyinfu_27\n  rotate: false\n  xy: 1804, 672\n  size: 62, 249\n  orig: 71, 254\n  offset: 2, 4\n  index: -1\nlunzhouyinfu/lunzhouyinfu_28\n  rotate: false\n  xy: 1740, 415\n  size: 63, 250\n  orig: 71, 254\n  offset: 2, 4\n  index: -1\nlunzhouyinfu/lunzhouyinfu_29\n  rotate: false\n  xy: 1716, 162\n  size: 57, 249\n  orig: 71, 254\n  offset: 3, 4\n  index: -1\nlunzhouyinfu/lunzhouyinfu_3\n  rotate: false\n  xy: 1868, 672\n  size: 56, 249\n  orig: 71, 254\n  offset: 6, 4\n  index: -1\nlunzhouyinfu/lunzhouyinfu_30\n  rotate: false\n  xy: 1869, 424\n  size: 54, 246\n  orig: 71, 254\n  offset: 5, 4\n  index: -1\nlunzhouyinfu/lunzhouyinfu_4\n  rotate: false\n  xy: 1680, 413\n  size: 58, 250\n  orig: 71, 254\n  offset: 5, 4\n  index: -1\nlunzhouyinfu/lunzhouyinfu_5\n  rotate: false\n  xy: 1656, 117\n  size: 58, 250\n  orig: 71, 254\n  offset: 6, 4\n  index: -1\nlunzhouyinfu/lunzhouyinfu_6\n  rotate: false\n  xy: 1078, 0\n  size: 61, 251\n  orig: 71, 254\n  offset: 5, 3\n  index: -1\nlunzhouyinfu/lunzhouyinfu_7\n  rotate: false\n  xy: 1676, 665\n  size: 62, 252\n  orig: 71, 254\n  offset: 5, 2\n  index: -1\nlunzhouyinfu/lunzhouyinfu_8\n  rotate: false\n  xy: 1740, 667\n  size: 62, 250\n  orig: 71, 254\n  offset: 4, 2\n  index: -1\nlunzhouyinfu/lunzhouyinfu_9\n  rotate: false\n  xy: 1549, 371\n  size: 64, 240\n  orig: 71, 254\n  offset: 3, 2\n  index: -1\nmenghei\n  rotate: false\n  xy: 1405, 48\n  size: 159, 76\n  orig: 159, 76\n  offset: 0, 0\n  index: -1\nmenghei/menghei_1\n  rotate: false\n  xy: 1090, 465\n  size: 321, 157\n  orig: 363, 197\n  offset: 21, 6\n  index: -1\nmenghei/menghei_10\n  rotate: false\n  xy: 0, 1019\n  size: 359, 148\n  orig: 363, 197\n  offset: 0, 15\n  index: -1\nmenghei/menghei_11\n  rotate: false\n  xy: 0, 720\n  size: 358, 146\n  orig: 363, 197\n  offset: 4, 17\n  index: -1\nmenghei/menghei_12\n  rotate: false\n  xy: 361, 1022\n  size: 360, 145\n  orig: 363, 197\n  offset: 3, 18\n  index: -1\nmenghei/menghei_13\n  rotate: false\n  xy: 723, 1023\n  size: 360, 144\n  orig: 363, 197\n  offset: 3, 19\n  index: -1\nmenghei/menghei_14\n  rotate: false\n  xy: 1085, 1024\n  size: 361, 143\n  orig: 363, 197\n  offset: 2, 20\n  index: -1\nmenghei/menghei_15\n  rotate: false\n  xy: 1448, 1025\n  size: 361, 142\n  orig: 363, 197\n  offset: 2, 21\n  index: -1\nmenghei/menghei_16\n  rotate: false\n  xy: 0, 577\n  size: 361, 141\n  orig: 363, 197\n  offset: 2, 22\n  index: -1\nmenghei/menghei_17\n  rotate: false\n  xy: 361, 884\n  size: 361, 136\n  orig: 363, 197\n  offset: 2, 27\n  index: -1\nmenghei/menghei_18\n  rotate: false\n  xy: 728, 479\n  size: 360, 130\n  orig: 363, 197\n  offset: 3, 37\n  index: -1\nmenghei/menghei_19\n  rotate: false\n  xy: 728, 611\n  size: 360, 134\n  orig: 363, 197\n  offset: 3, 38\n  index: -1\nmenghei/menghei_2\n  rotate: false\n  xy: 1090, 624\n  size: 322, 159\n  orig: 363, 197\n  offset: 21, 4\n  index: -1\nmenghei/menghei_20\n  rotate: false\n  xy: 724, 884\n  size: 358, 137\n  orig: 363, 197\n  offset: 3, 39\n  index: -1\nmenghei/menghei_21\n  rotate: false\n  xy: 360, 747\n  size: 362, 135\n  orig: 363, 197\n  offset: 1, 46\n  index: -1\nmenghei/menghei_22\n  rotate: false\n  xy: 724, 747\n  size: 362, 135\n  orig: 363, 197\n  offset: 1, 49\n  index: -1\nmenghei/menghei_23\n  rotate: false\n  xy: 363, 612\n  size: 363, 133\n  orig: 363, 197\n  offset: 0, 54\n  index: -1\nmenghei/menghei_24\n  rotate: false\n  xy: 363, 492\n  size: 363, 118\n  orig: 363, 197\n  offset: 0, 73\n  index: -1\nmenghei/menghei_25\n  rotate: false\n  xy: 350, 371\n  size: 363, 119\n  orig: 363, 197\n  offset: 0, 75\n  index: -1\nmenghei/menghei_26\n  rotate: false\n  xy: 715, 356\n  size: 363, 121\n  orig: 363, 197\n  offset: 0, 76\n  index: -1\nmenghei/menghei_27\n  rotate: false\n  xy: 336, 254\n  size: 363, 115\n  orig: 363, 197\n  offset: 0, 82\n  index: -1\nmenghei/menghei_28\n  rotate: false\n  xy: 701, 245\n  size: 363, 109\n  orig: 363, 197\n  offset: 0, 88\n  index: -1\nmenghei/menghei_29\n  rotate: false\n  xy: 1448, 919\n  size: 352, 104\n  orig: 363, 197\n  offset: 0, 93\n  index: -1\nmenghei/menghei_3\n  rotate: false\n  xy: 1088, 862\n  size: 326, 160\n  orig: 363, 197\n  offset: 17, 3\n  index: -1\nmenghei/menghei_30\n  rotate: false\n  xy: 0, 8\n  size: 330, 92\n  orig: 363, 197\n  offset: 20, 105\n  index: -1\nmenghei/menghei_31\n  rotate: false\n  xy: 332, 7\n  size: 320, 89\n  orig: 363, 197\n  offset: 28, 108\n  index: -1\nmenghei/menghei_32\n  rotate: false\n  xy: 654, 1\n  size: 320, 84\n  orig: 363, 197\n  offset: 28, 111\n  index: -1\nmenghei/menghei_33\n  rotate: false\n  xy: 1088, 785\n  size: 319, 75\n  orig: 363, 197\n  offset: 28, 120\n  index: -1\nmenghei/menghei_34\n  rotate: false\n  xy: 1080, 388\n  size: 317, 75\n  orig: 363, 197\n  offset: 30, 121\n  index: -1\nmenghei/menghei_35\n  rotate: false\n  xy: 1080, 316\n  size: 317, 70\n  orig: 363, 197\n  offset: 30, 126\n  index: -1\nmenghei/menghei_36\n  rotate: false\n  xy: 1066, 253\n  size: 317, 61\n  orig: 363, 197\n  offset: 30, 135\n  index: -1\nmenghei/menghei_37\n  rotate: false\n  xy: 1416, 859\n  size: 222, 58\n  orig: 363, 197\n  offset: 114, 138\n  index: -1\nmenghei/menghei_38\n  rotate: false\n  xy: 1566, 68\n  size: 171, 47\n  orig: 363, 197\n  offset: 114, 145\n  index: -1\nmenghei/menghei_39\n  rotate: false\n  xy: 1405, 9\n  size: 149, 37\n  orig: 363, 197\n  offset: 114, 150\n  index: -1\nmenghei/menghei_4\n  rotate: false\n  xy: 0, 102\n  size: 332, 159\n  orig: 363, 197\n  offset: 14, 4\n  index: -1\nmenghei/menghei_5\n  rotate: false\n  xy: 675, 87\n  size: 331, 156\n  orig: 363, 197\n  offset: 12, 7\n  index: -1\nmenghei/menghei_6\n  rotate: false\n  xy: 0, 263\n  size: 334, 160\n  orig: 363, 197\n  offset: 10, 3\n  index: -1\nmenghei/menghei_7\n  rotate: false\n  xy: 334, 98\n  size: 339, 154\n  orig: 363, 197\n  offset: 8, 9\n  index: -1\nmenghei/menghei_8\n  rotate: false\n  xy: 0, 425\n  size: 348, 150\n  orig: 363, 197\n  offset: 3, 13\n  index: -1\nmenghei/menghei_9\n  rotate: false\n  xy: 0, 868\n  size: 355, 149\n  orig: 363, 197\n  offset: 0, 14\n  index: -1\n","textures":[{"__uuid__":"cc6hMy+zRPbYh+kXSQrS04"}],"textureNames":["lunzhou_01.png"]}